{"duration":998,"records":[{"duration":358,"stepId":"io.quarkus.vertx.http.deployment.StaticResourcesProcessor#collectStaticResources","started":"23:05:10.047","dependents":[388],"id":376,"thread":"build-49"},{"duration":288,"stepId":"io.quarkus.deployment.steps.MainClassBuildStep#build","started":"23:05:10.706","dependents":[],"id":416,"thread":"build-55"},{"duration":125,"stepId":"io.quarkus.deployment.ide.IdeProcessor#detectRunningIdeProcesses","started":"23:05:10.039","dependents":[248],"id":247,"thread":"build-34"},{"duration":118,"stepId":"io.quarkus.vertx.http.deployment.webjar.WebJarProcessor#processWebJarDevMode","started":"23:05:10.498","dependents":[400,401,402,416,403],"id":399,"thread":"build-54"},{"duration":112,"stepId":"io.quarkus.smallrye.openapi.deployment.SmallRyeOpenApiProcessor#build","started":"23:05:10.233","dependents":[416],"id":353,"thread":"build-52"},{"duration":109,"stepId":"io.quarkus.devui.deployment.DevUIProcessor#getAllExtensions","started":"23:05:10.386","dependents":[394,401,399,395],"id":393,"thread":"build-34"},{"duration":70,"stepId":"io.quarkus.devui.deployment.BuildTimeContentProcessor#createIndexHtmlTemplate","started":"23:05:10.522","dependents":[398],"id":397,"thread":"build-34"},{"duration":68,"stepId":"io.quarkus.vertx.http.deployment.devmode.console.DevConsoleProcessor#setupDeploymentSideHandling","started":"23:05:10.634","dependents":[413,411,412],"id":410,"thread":"build-39"},{"duration":66,"stepId":"io.quarkus.deployment.steps.ConfigDescriptionBuildStep#createConfigDescriptions","started":"23:05:10.003","dependents":[311,310,306,410],"id":246,"thread":"build-5"},{"duration":59,"stepId":"io.quarkus.arc.deployment.ArcProcessor#generateResources","started":"23:05:10.378","dependents":[378,416,415,391],"id":377,"thread":"build-55"},{"duration":54,"stepId":"io.quarkus.arc.deployment.ArcProcessor#registerBeans","started":"23:05:10.250","dependents":[337,345,339,351,343,336,340,338,341,342,346,350,349],"id":335,"thread":"build-54"},{"duration":50,"stepId":"io.quarkus.arc.deployment.ArcProcessor#validate","started":"23:05:10.322","dependents":[372,359,360,370,371,362,361,363,364,377,391,365],"id":358,"thread":"build-45"},{"duration":49,"stepId":"io.quarkus.deployment.steps.ClassTransformingBuildStep#handleClassTransformation","started":"23:05:10.434","dependents":[392],"id":391,"thread":"build-54"},{"duration":48,"stepId":"io.quarkus.hibernate.orm.deployment.HibernateOrmProcessor#enhancerDomainObjects","started":"23:05:10.314","dependents":[355,391,356],"id":354,"thread":"build-54"},{"duration":47,"stepId":"io.quarkus.arc.deployment.BeanArchiveProcessor#build","started":"23:05:10.185","dependents":[322,319,346,318,333,321,324,349,329,328,320],"id":317,"thread":"build-29"},{"duration":33,"stepId":"io.quarkus.devservices.deployment.DevServicesProcessor#config","started":"23:05:10.187","dependents":[314,315,316],"id":313,"thread":"build-54"},{"duration":21,"stepId":"io.quarkus.devui.deployment.DevUIProcessor#registerDevUiHandlers","started":"23:05:10.610","dependents":[407,416,410,405],"id":404,"thread":"build-15"},{"duration":17,"stepId":"io.quarkus.deployment.dev.HotDeploymentWatchedFileBuildStep#setupWatchedFileHotDeployment","started":"23:05:10.184","dependents":[413,411,412],"id":312,"thread":"build-17"},{"duration":16,"stepId":"io.quarkus.resteasy.common.deployment.ResteasyCommonProcessor#setupProviders","started":"23:05:10.233","dependents":[360,358,329,415],"id":328,"thread":"build-14"},{"duration":15,"stepId":"io.quarkus.devui.deployment.BuildTimeContentProcessor#createBuildTimeConstJsTemplate","started":"23:05:10.506","dependents":[398,397],"id":396,"thread":"build-15"},{"duration":13,"stepId":"io.quarkus.smallrye.context.deployment.SmallRyeContextPropagationProcessor#build","started":"23:05:10.027","dependents":[345,416,350,343],"id":233,"thread":"build-32"},{"duration":11,"stepId":"io.quarkus.deployment.steps.CombinedIndexBuildStep#build","started":"23:05:10.166","dependents":[370,332,295,263,255,291,356,262,322,342,256,269,257,331,258,297,259,389,273,260,319,261,271,355,281,286,283,264,265,266,268,328,267,270,340,333,274,363,290,301,284,275,277,276,287,272,329,285,280],"id":254,"thread":"build-34"},{"duration":11,"stepId":"io.quarkus.arc.deployment.devconsole.ArcDevConsoleProcessor#collectBeanInfo","started":"23:05:10.370","dependents":[374,403,410,373],"id":372,"thread":"build-54"},{"duration":10,"stepId":"io.quarkus.deployment.steps.BannerProcessor#recordBanner","started":"23:05:10.025","dependents":[416,301],"id":201,"thread":"build-24"},{"duration":10,"stepId":"io.quarkus.deployment.steps.ApplicationIndexBuildStep#build","started":"23:05:10.030","dependents":[232,242,333,336],"id":229,"thread":"build-38"},{"duration":10,"stepId":"io.quarkus.vertx.http.deployment.devmode.console.ConfigEditorProcessor#config","started":"23:05:10.187","dependents":[314,413,416,403,410],"id":311,"thread":"build-43"},{"duration":9,"stepId":"io.quarkus.devui.deployment.menu.ConfigurationProcessor#registerConfigs","started":"23:05:10.187","dependents":[416],"id":310,"thread":"build-55"},{"duration":9,"stepId":"io.quarkus.deployment.ide.IdeProcessor#detectIdeFiles","started":"23:05:10.034","dependents":[248],"id":240,"thread":"build-55"},{"duration":8,"stepId":"io.quarkus.devui.deployment.BuildTimeContentProcessor#createBuildTimeData","started":"23:05:10.498","dependents":[396,397],"id":395,"thread":"build-34"},{"duration":8,"stepId":"io.quarkus.resteasy.deployment.ResteasyStandaloneBuildStep#addDefaultAuthFailureHandler","started":"23:05:10.001","dependents":[408,416,390],"id":40,"thread":"build-8"},{"duration":7,"stepId":"io.quarkus.arc.deployment.SyntheticBeansProcessor#initRuntime","started":"23:05:10.306","dependents":[413,416,411,351,347,412,382,348],"id":345,"thread":"build-43"},{"duration":7,"stepId":"io.quarkus.arc.deployment.staticmethods.InterceptedStaticMethodsProcessor#collectInterceptedStaticMethods","started":"23:05:10.306","dependents":[360,379,358,349],"id":346,"thread":"build-55"},{"duration":7,"stepId":"io.quarkus.vertx.http.deployment.StaticResourcesProcessor#runtimeInit","started":"23:05:10.434","dependents":[408,416],"id":388,"thread":"build-70"},{"duration":7,"stepId":"io.quarkus.vertx.deployment.VertxProcessor#currentContextFactory","started":"23:05:10.003","dependents":[416,377],"id":41,"thread":"build-9"},{"duration":6,"stepId":"io.quarkus.devui.deployment.menu.ContinuousTestingProcessor#continuousTestingState","started":"23:05:10.434","dependents":[416],"id":387,"thread":"build-68"},{"duration":6,"stepId":"io.quarkus.deployment.steps.ConfigGenerationBuildStep#checkForBuildTimeConfigChange","started":"23:05:10.016","dependents":[416],"id":159,"thread":"build-12"},{"duration":6,"stepId":"io.quarkus.vertx.http.deployment.devmode.console.DevConsoleProcessor#setupDevConsoleRoutes_adbb72d9f4bdcfb494014038ab4871b34b3c24d5","started":"23:05:10.610","dependents":[407,416,410,405],"id":403,"thread":"build-55"},{"duration":6,"stepId":"io.quarkus.deployment.index.ApplicationArchiveBuildStep#build","started":"23:05:10.040","dependents":[243,259,295,245,386,376,391,356,253,254,361,317,244],"id":242,"thread":"build-26"},{"duration":6,"stepId":"io.quarkus.vertx.http.deployment.devmode.console.DevConsoleProcessor#collectTemplates","started":"23:05:10.018","dependents":[410],"id":169,"thread":"build-15"},{"duration":5,"stepId":"io.quarkus.arc.deployment.SyntheticBeansProcessor#initRegular","started":"23:05:10.306","dependents":[351],"id":343,"thread":"build-17"},{"duration":5,"stepId":"io.quarkus.deployment.logging.LoggingResourceProcessor#setupLoggingRuntimeInit","started":"23:05:10.179","dependents":[416,403,410,304,415,409],"id":301,"thread":"build-29"},{"duration":4,"stepId":"io.quarkus.smallrye.context.deployment.SmallRyeContextPropagationProcessor#buildStatic","started":"23:05:10.035","dependents":[416],"id":226,"thread":"build-43"},{"duration":4,"stepId":"io.quarkus.arc.deployment.SplitPackageProcessor#splitPackageDetection","started":"23:05:10.047","dependents":[377],"id":245,"thread":"build-55"},{"duration":4,"stepId":"io.quarkus.arc.deployment.SyntheticBeansProcessor#initStatic","started":"23:05:10.314","dependents":[416,351],"id":350,"thread":"build-17"},{"duration":4,"stepId":"io.quarkus.vertx.core.deployment.VertxCoreProcessor#build_9fb3ce360263cc99d07c9172ec2feeaa85afcc1a","started":"23:05:10.015","dependents":[407,134,408,345,413,411,389,388,343,414,344,416,350,412,153],"id":129,"thread":"build-10"},{"duration":4,"stepId":"io.quarkus.vertx.deployment.VertxProcessor#build","started":"23:05:10.306","dependents":[413,416,411,415,412],"id":344,"thread":"build-45"},{"duration":3,"stepId":"io.quarkus.deployment.logging.LoggingResourceProcessor#setupStackTraceFormatter","started":"23:05:10.166","dependents":[301],"id":253,"thread":"build-55"},{"duration":3,"stepId":"io.quarkus.vertx.http.deployment.devmode.console.DevConsoleProcessor#handler","started":"23:05:10.010","dependents":[416,403,301],"id":52,"thread":"build-8"},{"duration":3,"stepId":"io.quarkus.vertx.http.deployment.VertxHttpProcessor#finalizeRouter","started":"23:05:10.634","dependents":[413,416,411,412,409],"id":408,"thread":"build-15"},{"duration":3,"stepId":"io.quarkus.vertx.core.deployment.VertxCoreProcessor#createVertxThreadFactory","started":"23:05:10.000","dependents":[57,416],"id":32,"thread":"build-4"},{"duration":2,"stepId":"io.quarkus.deployment.steps.ConfigGenerationBuildStep#buildTimeRunTimeConfig","started":"23:05:10.011","dependents":[369,415],"id":50,"thread":"build-3"},{"duration":2,"stepId":"io.quarkus.smallrye.openapi.deployment.SmallRyeOpenApiProcessor#registerAutoSecurityFilter","started":"23:05:10.233","dependents":[345,416,350,343],"id":327,"thread":"build-29"},{"duration":2,"stepId":"io.quarkus.vertx.http.deployment.devmode.ArcDevProcessor#registerRoutes","started":"23:05:10.370","dependents":[407,406,416,410,405,377],"id":371,"thread":"build-43"},{"duration":2,"stepId":"io.quarkus.devui.deployment.DevUIProcessor#findAllJsonRPCMethods","started":"23:05:10.179","dependents":[396,381],"id":286,"thread":"build-43"},{"duration":2,"stepId":"io.quarkus.smallrye.openapi.deployment.SmallRyeOpenApiProcessor#configFiles","started":"23:05:10.012","dependents":[312],"id":53,"thread":"build-7"},{"duration":2,"stepId":"io.quarkus.resteasy.deployment.ResteasyStandaloneBuildStep#boot","started":"23:05:10.442","dependents":[407,408,416,410,405,390],"id":389,"thread":"build-20"},{"duration":2,"stepId":"io.quarkus.resteasy.deployment.ResteasyStandaloneBuildStep#staticInit","started":"23:05:10.434","dependents":[416,389],"id":386,"thread":"build-21"},{"duration":2,"stepId":"io.quarkus.vertx.http.deployment.VertxHttpProcessor#cors","started":"23:05:10.009","dependents":[408,416,390],"id":48,"thread":"build-7"},{"duration":2,"stepId":"io.quarkus.swaggerui.deployment.SwaggerUiProcessor#getSwaggerUiFinalDestination","started":"23:05:10.187","dependents":[399],"id":309,"thread":"build-14"},{"duration":2,"stepId":"io.quarkus.vertx.core.deployment.VertxCoreProcessor#eventLoopCount","started":"23:05:10.008","dependents":[416,414],"id":42,"thread":"build-4"},{"duration":2,"stepId":"io.quarkus.hibernate.orm.panache.deployment.PanacheHibernateResourceProcessor#validate","started":"23:05:10.370","dependents":[377],"id":370,"thread":"build-55"},{"duration":2,"stepId":"io.quarkus.smallrye.openapi.deployment.SmallRyeOpenApiProcessor#handler","started":"23:05:10.442","dependents":[407,406,416,410,405],"id":390,"thread":"build-55"},{"duration":2,"stepId":"io.quarkus.vertx.http.deployment.VertxHttpProcessor#initializeRouter","started":"23:05:10.634","dependents":[408,416],"id":407,"thread":"build-55"},{"duration":2,"stepId":"io.quarkus.devui.deployment.BuildTimeContentProcessor#gatherMvnpmJars","started":"23:05:10.030","dependents":[404,397],"id":188,"thread":"build-17"},{"duration":2,"stepId":"io.quarkus.hibernate.orm.deployment.HibernateOrmProcessor#build_7a4403d699506d83ac39616f3c11e5e1b448d863","started":"23:05:10.184","dependents":[416,377],"id":303,"thread":"build-40"},{"duration":2,"stepId":"io.quarkus.resteasy.deployment.ResteasyBuiltinsProcessor#addStaticResourcesExceptionMapper","started":"23:05:10.048","dependents":[416],"id":244,"thread":"build-51"},{"duration":2,"stepId":"io.quarkus.hibernate.orm.deployment.HibernateOrmCdiProcessor#generateJpaConfigBean","started":"23:05:10.037","dependents":[345,416,350,343],"id":228,"thread":"build-33"},{"duration":2,"stepId":"io.quarkus.agroal.deployment.AgroalProcessor#generateDataSourceBeans","started":"23:05:10.181","dependents":[294,295,345,416,350,343,302,382,348],"id":293,"thread":"build-45"},{"duration":2,"stepId":"io.quarkus.swaggerui.deployment.SwaggerUiProcessor#registerSwaggerUiHandler","started":"23:05:10.610","dependents":[407,416,410,405],"id":402,"thread":"build-39"},{"duration":2,"stepId":"io.quarkus.datasource.deployment.devservices.DevUIDatasourceProcessor#devConsoleCleanDatabaseHandler","started":"23:05:10.042","dependents":[416,403,410],"id":241,"thread":"build-46"},{"duration":2,"stepId":"io.quarkus.deployment.steps.ThreadPoolSetup#createExecutor","started":"23:05:10.012","dependents":[68,233,408,72,416,389,65,129],"id":57,"thread":"build-20"},{"duration":2,"stepId":"io.quarkus.jackson.deployment.JacksonProcessor#jacksonSupport","started":"23:05:10.180","dependents":[345,416,350,343],"id":287,"thread":"build-54"},{"duration":2,"stepId":"io.quarkus.vertx.http.deployment.VertxHttpProcessor#bodyHandler","started":"23:05:10.012","dependents":[408,416,403],"id":56,"thread":"build-4"},{"duration":2,"stepId":"io.quarkus.vertx.core.deployment.VertxCoreProcessor#createVertxContextHandlers","started":"23:05:10.001","dependents":[57,72,416],"id":22,"thread":"build-3"},{"duration":2,"stepId":"io.quarkus.vertx.core.deployment.VertxCoreProcessor#ioThreadDetector","started":"23:05:10.021","dependents":[416,167],"id":163,"thread":"build-7"},{"duration":2,"stepId":"io.quarkus.devui.deployment.menu.ConfigurationProcessor#registerJsonRpcService","started":"23:05:10.015","dependents":[345,250,416,350,343,286],"id":102,"thread":"build-11"},{"duration":1,"stepId":"io.quarkus.vertx.http.deployment.devmode.console.DevConsoleProcessor#setupConsole","started":"23:05:10.014","dependents":[413,411,412],"id":82,"thread":"build-3"},{"duration":1,"stepId":"io.quarkus.hibernate.orm.deployment.HibernateOrmCdiProcessor#generateDataSourceBeans","started":"23:05:10.184","dependents":[345,416,333,317,350,343],"id":302,"thread":"build-55"},{"duration":1,"stepId":"io.quarkus.vertx.http.deployment.VertxHttpProcessor#preinitializeRouter","started":"23:05:10.019","dependents":[407,345,416,350,343],"id":153,"thread":"build-4"},{"duration":1,"stepId":"io.quarkus.agroal.deployment.AgroalProcessor#generateDataSourceSupportBean","started":"23:05:10.038","dependents":[360,358,345,416,333,317,350,343],"id":227,"thread":"build-26"},{"duration":1,"stepId":"io.quarkus.arc.deployment.ConfigBuildStep#registerConfigRootsAsBeans","started":"23:05:10.027","dependents":[345,350,343],"id":183,"thread":"build-16"},{"duration":1,"stepId":"io.quarkus.resteasy.server.common.deployment.ResteasyServerCommonProcessor#build","started":"23:05:10.250","dependents":[360,332,358,386,384,333,415,391,330],"id":329,"thread":"build-29"},{"duration":1,"stepId":"io.quarkus.arc.deployment.ArcProcessor#registerSyntheticObservers","started":"23:05:10.322","dependents":[360,358,352,415,377],"id":351,"thread":"build-45"},{"duration":1,"stepId":"io.quarkus.vertx.http.deployment.devmode.ArcDevProcessor#eventsEndpoint","started":"23:05:10.015","dependents":[416,403,410],"id":87,"thread":"build-7"},{"duration":1,"stepId":"io.quarkus.arc.deployment.devconsole.ArcDevConsoleProcessor#exposeArcContainer","started":"23:05:10.029","dependents":[413,416],"id":186,"thread":"build-16"},{"duration":1,"stepId":"io.quarkus.devui.deployment.BuildTimeContentProcessor#loadAllBuildTimeTemplates","started":"23:05:10.586","dependents":[404],"id":398,"thread":"build-15"},{"duration":1,"stepId":"io.quarkus.narayana.jta.deployment.NarayanaJtaProcessor#build","started":"23:05:10.179","dependents":[293,416,333,317,415,348],"id":284,"thread":"build-52"},{"duration":1,"stepId":"io.quarkus.resteasy.server.common.deployment.ResteasyServerCommonProcessor#registerCompatibleAnnotationPrefixes","started":"23:05:10.023","dependents":[329],"id":170,"thread":"build-19"},{"duration":1,"stepId":"io.quarkus.devui.deployment.logstream.LogStreamProcessor#handler","started":"23:05:10.021","dependents":[416,301],"id":160,"thread":"build-10"},{"duration":1,"stepId":"io.quarkus.vertx.http.deployment.devmode.console.DevConsoleProcessor#buildTimeTemplates","started":"23:05:10.386","dependents":[413,411,412],"id":374,"thread":"build-17"},{"duration":1,"stepId":"io.quarkus.deployment.dev.testing.TestTracingProcessor#testConsoleCommand","started":"23:05:10.178","dependents":[314],"id":281,"thread":"build-36"},{"duration":1,"stepId":"io.quarkus.hibernate.orm.deployment.HibernateOrmProcessor#defineJpaEntities","started":"23:05:10.181","dependents":[392,298,295,289,415,290,382,297,303,354,312],"id":288,"thread":"build-52"},{"duration":1,"stepId":"io.quarkus.vertx.http.deployment.HttpSecurityProcessor#initBasicAuth","started":"23:05:10.009","dependents":[326,345,416,350,343,327],"id":44,"thread":"build-12"},{"duration":1,"stepId":"io.quarkus.jackson.deployment.JacksonProcessor#register","started":"23:05:10.178","dependents":[332,333,317,415],"id":273,"thread":"build-32"},{"duration":1,"stepId":"io.quarkus.vertx.http.deployment.devmode.tests.TestsProcessor#setupTestRoutes","started":"23:05:10.025","dependents":[407,181,416,410,405],"id":180,"thread":"build-26"},{"duration":1,"stepId":"io.quarkus.vertx.deployment.VertxProcessor#collectEventConsumers","started":"23:05:10.306","dependents":[344,351],"id":341,"thread":"build-14"},{"duration":1,"stepId":"io.quarkus.deployment.steps.ConfigGenerationBuildStep#watchConfigFiles","started":"23:05:10.021","dependents":[312],"id":161,"thread":"build-11"},{"duration":1,"stepId":"io.quarkus.smallrye.openapi.deployment.SmallRyeOpenApiProcessor#addAutoFilters","started":"23:05:10.233","dependents":[353],"id":326,"thread":"build-54"},{"duration":1,"stepId":"io.quarkus.datasource.deployment.devservices.DevServicesDatasourceProcessor#launchDatabases","started":"23:05:10.185","dependents":[305,313],"id":304,"thread":"build-43"},{"duration":1,"stepId":"io.quarkus.devui.deployment.BuildTimeContentProcessor#mapPageBuildTimeData","started":"23:05:10.386","dependents":[396],"id":375,"thread":"build-36"},{"duration":1,"stepId":"io.quarkus.vertx.http.deployment.devmode.ArcDevProcessor#invocationsEndpoint","started":"23:05:10.033","dependents":[416,403,410],"id":197,"thread":"build-43"},{"duration":1,"stepId":"io.quarkus.arc.deployment.ArcProcessor#initialize","started":"23:05:10.250","dependents":[372,334,335,349],"id":333,"thread":"build-54"},{"duration":1,"stepId":"io.quarkus.hibernate.orm.deployment.HibernateOrmProcessor#jpaEntitiesIndexer","started":"23:05:10.179","dependents":[392,288],"id":285,"thread":"build-14"},{"duration":1,"stepId":"io.quarkus.resteasy.common.deployment.ResteasyCommonProcessor#setupResteasyInjection","started":"23:05:10.434","dependents":[386,416,384],"id":383,"thread":"build-55"},{"duration":0,"stepId":"io.quarkus.hibernate.orm.deployment.GraalVMFeatures#registerGeneratorClassesForReflections","started":"23:05:10.015","dependents":[415],"id":80,"thread":"build-20"},{"duration":0,"stepId":"io.quarkus.datasource.deployment.DataSourcesExcludedFromHealthChecksProcessor#produceBean","started":"23:05:10.039","dependents":[345,416,350,343],"id":222,"thread":"build-22"},{"duration":0,"stepId":"io.quarkus.arc.deployment.BuildTimeEnabledProcessor#unlessBuildProperty","started":"23:05:10.178","dependents":[329,279,278],"id":257,"thread":"build-50"},{"duration":0,"stepId":"io.quarkus.vertx.deployment.VertxProcessor#registerVerticleClasses","started":"23:05:10.178","dependents":[415],"id":258,"thread":"build-48"},{"duration":0,"stepId":"io.quarkus.hibernate.orm.deployment.HibernateOrmProcessor#parsePersistenceXmlDescriptors","started":"23:05:10.032","dependents":[295,190],"id":189,"thread":"build-13"},{"duration":0,"stepId":"io.quarkus.vertx.http.deployment.devmode.tests.TestsProcessor#toggleTestRunner","started":"23:05:10.019","dependents":[403,410],"id":125,"thread":"build-2"},{"duration":0,"stepId":"io.quarkus.deployment.dev.IsolatedDevModeMain$5$1@24927ba0","started":"23:05:10.021","dependents":[333],"id":152,"thread":"build-20"},{"duration":0,"stepId":"io.quarkus.datasource.deployment.devservices.DevUIDatasourceProcessor#create","started":"23:05:10.023","dependents":[393,375],"id":164,"thread":"build-18"},{"duration":0,"stepId":"io.quarkus.smallrye.openapi.deployment.SmallRyeOpenApiProcessor#registerOpenApiSchemaClassesForReflection","started":"23:05:10.233","dependents":[332,415],"id":325,"thread":"build-52"},{"duration":0,"stepId":"io.quarkus.deployment.JniProcessor#setupJni","started":"23:05:10.001","dependents":[219],"id":16,"thread":"build-5"},{"duration":0,"stepId":"io.quarkus.hibernate.orm.deployment.dev.HibernateOrmDevConsoleProcessor#exposeInfo","started":"23:05:10.030","dependents":[413],"id":187,"thread":"build-26"},{"duration":0,"stepId":"io.quarkus.hibernate.orm.deployment.HibernateOrmProcessor#registerBeans","started":"23:05:10.184","dependents":[360,358,333,317],"id":297,"thread":"build-36"},{"duration":0,"stepId":"io.quarkus.deployment.steps.ConfigGenerationBuildStep#runtimeDefaultsConfig","started":"23:05:10.370","dependents":[369,415],"id":368,"thread":"build-29"},{"duration":0,"stepId":"io.quarkus.deployment.console.ConsoleProcessor#setupConsole","started":"23:05:10.014","dependents":[218,181,253,304,252],"id":54,"thread":"build-7"},{"duration":0,"stepId":"io.quarkus.deployment.console.ConsoleProcessor#installCliCommands","started":"23:05:10.217","dependents":[413,411,412],"id":314,"thread":"build-17"},{"duration":0,"stepId":"io.quarkus.vertx.core.deployment.VertxCoreProcessor#cleanupVertxWarnings","started":"23:05:10.041","dependents":[301,239],"id":231,"thread":"build-44"},{"duration":0,"stepId":"io.quarkus.hibernate.orm.panache.common.deployment.PanacheJpaCommonResourceProcessor#lookupNamedQueries_5a86a91ed8ef1aa483288c8239df231983eeb766","started":"23:05:10.182","dependents":[292],"id":290,"thread":"build-43"},{"duration":0,"stepId":"io.quarkus.arc.deployment.ArcProcessor#loggerProducer","started":"23:05:10.018","dependents":[333,317],"id":107,"thread":"build-7"},{"duration":0,"stepId":"io.quarkus.resteasy.deployment.ResteasyServletProcessor#webXmlMapping","started":"23:05:10.020","dependents":[329],"id":139,"thread":"build-6"},{"duration":0,"stepId":"io.quarkus.arc.deployment.BuildTimeEnabledProcessor#buildExclusions","started":"23:05:10.180","dependents":[322],"id":279,"thread":"build-17"},{"duration":0,"stepId":"io.quarkus.arc.deployment.ConfigBuildStep#additionalBeans","started":"23:05:10.018","dependents":[333,317],"id":110,"thread":"build-4"},{"duration":0,"stepId":"io.quarkus.resteasy.deployment.ResteasyBuiltinsProcessor#vertxProviders","started":"23:05:10.015","dependents":[328],"id":61,"thread":"build-10"},{"duration":0,"stepId":"io.quarkus.vertx.http.deployment.devmode.tests.TestsProcessor#runFailedTests","started":"23:05:10.000","dependents":[403,410],"id":2,"thread":"build-3"},{"duration":0,"stepId":"io.quarkus.deployment.steps.ConfigGenerationBuildStep#setupConfigOverride","started":"23:05:10.018","dependents":[],"id":119,"thread":"build-2"},{"duration":0,"stepId":"io.quarkus.deployment.console.ConsoleProcessor#setupExceptionHandler","started":"23:05:10.166","dependents":[253],"id":252,"thread":"build-51"},{"duration":0,"stepId":"io.quarkus.deployment.steps.ProfileBuildStep#defaultProfile","started":"23:05:10.016","dependents":[368],"id":88,"thread":"build-15"},{"duration":0,"stepId":"io.quarkus.netty.deployment.NettyProcessor#registerQualifiers","started":"23:05:10.042","dependents":[333,317],"id":235,"thread":"build-48"},{"duration":0,"stepId":"io.quarkus.deployment.CollectionClassProcessor#setupCollectionClasses","started":"23:05:10.003","dependents":[415],"id":21,"thread":"build-6"},{"duration":0,"stepId":"io.quarkus.deployment.steps.CurateOutcomeBuildStep#removeResources","started":"23:05:10.030","dependents":[391],"id":185,"thread":"build-41"},{"duration":0,"stepId":"io.quarkus.arc.deployment.ConfigBuildStep#validateConfigMappingsInjectionPoints","started":"23:05:10.370","dependents":[369,366,367],"id":360,"thread":"build-52"},{"duration":0,"stepId":"io.quarkus.arc.deployment.ConfigBuildStep#vetoMPConfigProperties","started":"23:05:10.021","dependents":[333],"id":146,"thread":"build-3"},{"duration":0,"stepId":"io.quarkus.smallrye.context.deployment.SmallRyeContextPropagationProcessor#registerBean","started":"23:05:10.015","dependents":[333,317],"id":66,"thread":"build-15"},{"duration":0,"stepId":"io.quarkus.devui.deployment.menu.ContinuousTestingProcessor#createJsonRPCService","started":"23:05:10.016","dependents":[250,286],"id":90,"thread":"build-8"},{"duration":0,"stepId":"io.quarkus.credentials.CredentialsProcessor#unremoveable","started":"23:05:10.019","dependents":[360,358],"id":120,"thread":"build-3"},{"duration":0,"stepId":"io.quarkus.arc.deployment.HotDeploymentConfigBuildStep#startup","started":"23:05:10.015","dependents":[174],"id":55,"thread":"build-2"},{"duration":0,"stepId":"io.quarkus.deployment.ide.IdeProcessor#effectiveIde","started":"23:05:10.166","dependents":[249,253,410,251,395,252],"id":248,"thread":"build-5"},{"duration":0,"stepId":"io.quarkus.deployment.steps.AdditionalClassLoaderResourcesBuildStep#appendAdditionalClassloaderResources","started":"23:05:10.021","dependents":[254],"id":149,"thread":"build-7"},{"duration":0,"stepId":"io.quarkus.hibernate.orm.deployment.HibernateOrmProcessor#candidatesForFieldAccess","started":"23:05:10.182","dependents":[291],"id":289,"thread":"build-54"},{"duration":0,"stepId":"io.quarkus.deployment.steps.BootstrapConfigSetupBuildStep#setupBootstrapConfig","started":"23:05:10.005","dependents":[416,36],"id":35,"thread":"build-20"},{"duration":0,"stepId":"io.quarkus.resteasy.jackson.deployment.ResteasyJacksonProcessor#feature","started":"23:05:10.016","dependents":[416],"id":91,"thread":"build-20"},{"duration":0,"stepId":"io.quarkus.devui.deployment.BuildTimeContentProcessor#createKnownInternalImportMap","started":"23:05:10.014","dependents":[397],"id":63,"thread":"build-12"},{"duration":0,"stepId":"io.quarkus.deployment.logging.LoggingResourceProcessor#setupLoggingStaticInit","started":"23:05:10.003","dependents":[416],"id":18,"thread":"build-7"},{"duration":0,"stepId":"io.quarkus.vertx.deployment.VertxProcessor#unremovableBeans","started":"23:05:10.019","dependents":[360,358],"id":121,"thread":"build-11"},{"duration":0,"stepId":"io.quarkus.vertx.http.deployment.HttpSecurityProcessor#builtins","started":"23:05:10.178","dependents":[282,416,333,317,415],"id":264,"thread":"build-13"},{"duration":0,"stepId":"io.quarkus.deployment.index.ApplicationArchiveBuildStep#addConfiguredIndexedDependencies","started":"23:05:10.011","dependents":[242],"id":45,"thread":"build-20"},{"duration":0,"stepId":"io.quarkus.deployment.logging.LoggingResourceProcessor#setMinLevelForInitialConfigurator","started":"23:05:10.011","dependents":[416],"id":46,"thread":"build-6"},{"duration":0,"stepId":"io.quarkus.arc.deployment.ArcProcessor#quarkusApplication","started":"23:05:10.178","dependents":[333,317],"id":265,"thread":"build-16"},{"duration":0,"stepId":"io.quarkus.arc.deployment.init.InitializationTaskProcessor#startApplicationInitializer","started":"23:05:10.314","dependents":[416],"id":347,"thread":"build-45"},{"duration":0,"stepId":"io.quarkus.arc.deployment.ArcProcessor#marker","started":"23:05:10.003","dependents":[242],"id":20,"thread":"build-7"},{"duration":0,"stepId":"io.quarkus.hibernate.orm.panache.deployment.PanacheHibernateResourceProcessor#produceModel","started":"23:05:10.021","dependents":[285,354],"id":150,"thread":"build-9"},{"duration":0,"stepId":"io.quarkus.deployment.logging.LoggingResourceProcessor#setProperty","started":"23:05:10.019","dependents":[416],"id":130,"thread":"build-4"},{"duration":0,"stepId":"io.quarkus.narayana.jta.deployment.NarayanaJtaProcessor#transactionContext","started":"23:05:10.250","dependents":[335],"id":334,"thread":"build-14"},{"duration":0,"stepId":"io.quarkus.arc.deployment.AutoInjectFieldProcessor#autoInjectQualifiers","started":"23:05:10.233","dependents":[323,324,329],"id":320,"thread":"build-52"},{"duration":0,"stepId":"io.quarkus.deployment.logging.LoggingResourceProcessor#setUpDarkeningDefault","started":"23:05:10.018","dependents":[368],"id":106,"thread":"build-15"},{"duration":0,"stepId":"io.quarkus.resteasy.server.common.deployment.ResteasyServerCommonProcessor#processPathInterfaceImplementors","started":"23:05:10.179","dependents":[360,358,333,317],"id":275,"thread":"build-41"},{"duration":0,"stepId":"io.quarkus.hibernate.orm.deployment.HibernateOrmProcessor#multitenancy","started":"23:05:10.184","dependents":[360,358,345,416,350,343],"id":300,"thread":"build-43"},{"duration":0,"stepId":"io.quarkus.hibernate.orm.deployment.HibernateOrmProcessor#contributeQuarkusConfigToJpaModel","started":"23:05:10.004","dependents":[288],"id":33,"thread":"build-12"},{"duration":0,"stepId":"io.quarkus.deployment.steps.DevModeBuildStep#watchChanges","started":"23:05:10.004","dependents":[312],"id":34,"thread":"build-11"},{"duration":0,"stepId":"io.quarkus.vertx.core.deployment.VertxCoreProcessor#build_9d6b7122fb368970c50c3a870d1f672392cd8afb","started":"23:05:10.017","dependents":[219,415],"id":98,"thread":"build-6"},{"duration":0,"stepId":"io.quarkus.deployment.logging.LoggingWithPanacheProcessor#process","started":"23:05:10.178","dependents":[391],"id":262,"thread":"build-5"},{"duration":0,"stepId":"io.quarkus.vertx.http.deployment.HttpSecurityProcessor#setupAuthenticationMechanisms","started":"23:05:10.180","dependents":[326,408,416,333,317,377,390,327],"id":282,"thread":"build-55"},{"duration":0,"stepId":"io.quarkus.vertx.http.deployment.devmode.console.DevConsoleProcessor#config","started":"23:05:10.217","dependents":[374],"id":316,"thread":"build-55"},{"duration":0,"stepId":"io.quarkus.deployment.console.ConsoleProcessor#missingDevUIMessageHandler","started":"23:05:10.038","dependents":[413,411,412],"id":218,"thread":"build-29"},{"duration":0,"stepId":"io.quarkus.vertx.http.deployment.ManagementInterfaceSecurityProcessor#setupAuthenticationMechanisms","started":"23:05:10.037","dependents":[408,416,333,317,377],"id":214,"thread":"build-53"},{"duration":0,"stepId":"io.quarkus.jackson.deployment.JacksonProcessor#generateCustomizer","started":"23:05:10.180","dependents":[317],"id":283,"thread":"build-45"},{"duration":0,"stepId":"io.quarkus.deployment.dev.testing.TestTracingProcessor#sharedStateListener","started":"23:05:10.019","dependents":[181],"id":132,"thread":"build-6"},{"duration":0,"stepId":"io.quarkus.vertx.http.deployment.devmode.console.DevConsoleProcessor#runtimeTemplates","started":"23:05:10.706","dependents":[416],"id":413,"thread":"build-55"},{"duration":0,"stepId":"io.quarkus.resteasy.server.common.deployment.ResteasyLogFilterBuildStep#setupLogFilters","started":"23:05:10.040","dependents":[301,239],"id":230,"thread":"build-36"},{"duration":0,"stepId":"io.quarkus.resteasy.deployment.RestPathAnnotationProcessor#findRestPaths","started":"23:05:10.250","dependents":[333],"id":331,"thread":"build-29"},{"duration":0,"stepId":"io.quarkus.arc.deployment.ConfigBuildStep#validateConfigInjectionPoints","started":"23:05:10.370","dependents":[380],"id":359,"thread":"build-17"},{"duration":0,"stepId":"io.quarkus.vertx.core.deployment.VertxCoreProcessor#preventLoggerContention","started":"23:05:10.021","dependents":[179],"id":147,"thread":"build-6"},{"duration":0,"stepId":"io.quarkus.hibernate.orm.deployment.dev.HibernateOrmDevUIProcessor#additionalBeans","started":"23:05:10.027","dependents":[333,317],"id":177,"thread":"build-38"},{"duration":0,"stepId":"io.quarkus.deployment.ForkJoinPoolProcessor#setProperty","started":"23:05:10.015","dependents":[416],"id":60,"thread":"build-15"},{"duration":0,"stepId":"io.quarkus.vertx.http.deployment.devmode.tests.TestsProcessor#handleTestResult","started":"23:05:10.019","dependents":[403,410],"id":135,"thread":"build-9"},{"duration":0,"stepId":"io.quarkus.mutiny.deployment.MutinyProcessor#runtimeInit","started":"23:05:10.015","dependents":[416],"id":72,"thread":"build-12"},{"duration":0,"stepId":"io.quarkus.smallrye.openapi.deployment.SmallRyeOpenApiProcessor#classLoaderHack","started":"23:05:10.011","dependents":[416],"id":47,"thread":"build-10"},{"duration":0,"stepId":"io.quarkus.agroal.deployment.AgroalProcessor#build","started":"23:05:10.037","dependents":[219,293,220,333,317,415,227],"id":217,"thread":"build-52"},{"duration":0,"stepId":"io.quarkus.deployment.steps.DevServicesConfigBuildStep#setup","started":"23:05:10.186","dependents":[311,368,413,310,308,313,411,306,309,412,307],"id":305,"thread":"build-40"},{"duration":0,"stepId":"io.quarkus.deployment.pkg.steps.JarResultBuildStep#outputTarget","started":"23:05:10.004","dependents":[172,353,53],"id":28,"thread":"build-15"},{"duration":0,"stepId":"io.quarkus.netty.deployment.NettyProcessor#setNettyMachineId","started":"23:05:10.034","dependents":[416],"id":196,"thread":"build-54"},{"duration":0,"stepId":"io.quarkus.vertx.http.deployment.devmode.tests.TestsProcessor#runAllTests","started":"23:05:10.001","dependents":[403,410],"id":12,"thread":"build-6"},{"duration":0,"stepId":"io.quarkus.vertx.deployment.VertxProcessor#featureAndCapability","started":"23:05:10.004","dependents":[416,206],"id":29,"thread":"build-7"},{"duration":0,"stepId":"io.quarkus.arc.deployment.ConfigBuildStep#warnStaticInitInjectionPoints","started":"23:05:10.370","dependents":[368],"id":363,"thread":"build-36"},{"duration":0,"stepId":"io.quarkus.datasource.deployment.devservices.DevUIDatasourceProcessor#registerJsonRpcBackend","started":"23:05:10.015","dependents":[250,286],"id":71,"thread":"build-9"},{"duration":0,"stepId":"io.quarkus.arc.deployment.BuildTimeEnabledProcessor#unlessBuildProfile","started":"23:05:10.178","dependents":[329,279,278],"id":261,"thread":"build-44"},{"duration":0,"stepId":"io.quarkus.hibernate.orm.deployment.HibernateOrmProcessor#build_daeea4f2c9416db083cc1423ec1bf5c757ad2a16","started":"23:05:10.184","dependents":[355,416],"id":298,"thread":"build-54"},{"duration":0,"stepId":"io.quarkus.hibernate.orm.panache.deployment.PanacheHibernateResourceProcessor#marker","started":"23:05:10.015","dependents":[242],"id":62,"thread":"build-6"},{"duration":0,"stepId":"io.quarkus.jdbc.postgresql.deployment.JDBCPostgreSQLProcessor#configureAgroalConnection","started":"23:05:10.037","dependents":[333,317],"id":210,"thread":"build-52"},{"duration":0,"stepId":"io.quarkus.deployment.steps.ConfigGenerationBuildStep#generateConfigClass","started":"23:05:10.370","dependents":[415],"id":369,"thread":"build-17"},{"duration":0,"stepId":"io.quarkus.arc.deployment.AutoProducerMethodsProcessor#annotationTransformer","started":"23:05:10.233","dependents":[333],"id":321,"thread":"build-54"},{"duration":0,"stepId":"io.quarkus.hibernate.orm.panache.deployment.PanacheHibernateResourceProcessor#build","started":"23:05:10.362","dependents":[357,391],"id":355,"thread":"build-52"},{"duration":0,"stepId":"io.quarkus.deployment.recording.substitutions.AdditionalSubstitutionsBuildStep#additionalSubstitutions","started":"23:05:10.043","dependents":[416],"id":236,"thread":"build-49"},{"duration":0,"stepId":"io.quarkus.vertx.http.deployment.HttpSecurityProcessor#initMtlsClientAuth","started":"23:05:10.009","dependents":[345,416,350,343],"id":38,"thread":"build-10"},{"duration":0,"stepId":"io.quarkus.deployment.steps.RuntimeConfigSetupBuildStep#setupRuntimeConfig","started":"23:05:10.006","dependents":[293,44,42,37,129,39,348,327,48,57,215,38,159,201,153,284,301,407,408,402,56,389,388,390,414,409,298,416,228,412],"id":36,"thread":"build-11"},{"duration":0,"stepId":"io.quarkus.netty.deployment.NettyProcessor#cleanupUnsafeLog","started":"23:05:10.018","dependents":[301,239],"id":114,"thread":"build-11"},{"duration":0,"stepId":"io.quarkus.deployment.steps.CapabilityAggregationStep#provideCapabilities","started":"23:05:10.036","dependents":[206],"id":204,"thread":"build-54"},{"duration":0,"stepId":"io.quarkus.vertx.http.deployment.VertxHttpProcessor#config","started":"23:05:10.041","dependents":[369],"id":234,"thread":"build-45"},{"duration":0,"stepId":"io.quarkus.arc.deployment.ArcProcessor#registerContextPropagation","started":"23:05:10.035","dependents":[226],"id":198,"thread":"build-29"},{"duration":0,"stepId":"io.quarkus.hibernate.orm.panache.common.deployment.PanacheJpaCommonResourceProcessor#buildNamedQueryMap","started":"23:05:10.183","dependents":[416],"id":292,"thread":"build-54"},{"duration":0,"stepId":"io.quarkus.deployment.steps.ConfigBuildSteps#generateConfigSources","started":"23:05:10.021","dependents":[],"id":143,"thread":"build-11"},{"duration":0,"stepId":"io.quarkus.narayana.jta.deployment.NarayanaJtaProcessor#logCleanupFilters","started":"23:05:10.043","dependents":[301,239],"id":237,"thread":"build-50"},{"duration":0,"stepId":"io.quarkus.arc.deployment.BuildTimeEnabledProcessor#ifBuildProperty","started":"23:05:10.178","dependents":[329,279,278],"id":255,"thread":"build-51"},{"duration":0,"stepId":"io.quarkus.arc.deployment.ArcProcessor#feature","started":"23:05:10.015","dependents":[416],"id":73,"thread":"build-12"},{"duration":0,"stepId":"io.quarkus.vertx.http.deployment.devmode.tests.TestsProcessor#forceRestart","started":"23:05:10.015","dependents":[403,410],"id":77,"thread":"build-8"},{"duration":0,"stepId":"io.quarkus.deployment.recording.AnnotationProxyBuildStep#build","started":"23:05:10.041","dependents":[344],"id":232,"thread":"build-33"},{"duration":0,"stepId":"io.quarkus.vertx.core.deployment.VertxCoreProcessor#registerVerticleClasses","started":"23:05:10.179","dependents":[415],"id":271,"thread":"build-38"},{"duration":0,"stepId":"io.quarkus.arc.deployment.ArcProcessor#unremovableAsyncObserverExceptionHandlers","started":"23:05:10.017","dependents":[360,358],"id":100,"thread":"build-15"},{"duration":0,"stepId":"io.quarkus.hibernate.orm.deployment.HibernateOrmProcessor#enrollBeanValidationTypeSafeActivatorForReflection","started":"23:05:10.037","dependents":[415],"id":211,"thread":"build-47"},{"duration":0,"stepId":"io.quarkus.deployment.steps.PreloadClassesBuildStep#preInit","started":"23:05:10.018","dependents":[416],"id":115,"thread":"build-4"},{"duration":0,"stepId":"io.quarkus.arc.deployment.LookupConditionsProcessor#suppressConditionsGenerators","started":"23:05:10.226","dependents":[333],"id":318,"thread":"build-43"},{"duration":0,"stepId":"io.quarkus.swaggerui.deployment.SwaggerUiProcessor#brandingFiles","started":"23:05:10.018","dependents":[312],"id":105,"thread":"build-11"},{"duration":0,"stepId":"io.quarkus.resteasy.deployment.ResteasyBuiltinsProcessor#setupExceptionMapper","started":"23:05:10.001","dependents":[416,328],"id":15,"thread":"build-9"},{"duration":0,"stepId":"io.quarkus.vertx.http.deployment.ManagementInterfaceSecurityProcessor#initBasicAuth","started":"23:05:10.008","dependents":[345,416,350,343],"id":37,"thread":"build-6"},{"duration":0,"stepId":"io.quarkiverse.caffeine.deployment.devui.CaffeineDevUIProcessor#createCard","started":"23:05:10.027","dependents":[393,375],"id":182,"thread":"build-41"},{"duration":0,"stepId":"io.quarkus.deployment.pkg.steps.FileSystemResourcesBuildStep#notNormalMode","started":"23:05:10.025","dependents":[],"id":172,"thread":"build-23"},{"duration":0,"stepId":"io.quarkus.resteasy.deployment.ResteasyBuiltinsProcessor#addAdditionalEndpointsExceptionMapper","started":"23:05:10.634","dependents":[416],"id":406,"thread":"build-15"},{"duration":0,"stepId":"io.quarkus.arc.deployment.ConfigBuildStep#generateConfigProperties","started":"23:05:10.179","dependents":[360,342,363,415,364,340],"id":276,"thread":"build-24"},{"duration":0,"stepId":"io.quarkus.vertx.http.deployment.VertxHttpProcessor#filterMultipleVertxInstancesWarning","started":"23:05:10.017","dependents":[301,239],"id":97,"thread":"build-7"},{"duration":0,"stepId":"io.quarkus.arc.deployment.StartupBuildSteps#addScope","started":"23:05:10.021","dependents":[324],"id":151,"thread":"build-10"},{"duration":0,"stepId":"io.quarkus.resteasy.deployment.ResteasyServletProcessor#jaxrsConfig","started":"23:05:10.250","dependents":[331],"id":330,"thread":"build-54"},{"duration":0,"stepId":"io.quarkus.arc.deployment.ExecutorServiceProcessor#executorServiceBean","started":"23:05:10.015","dependents":[345,350,343],"id":65,"thread":"build-6"},{"duration":0,"stepId":"io.quarkus.deployment.steps.MainClassBuildStep#mainClassBuildStep","started":"23:05:10.178","dependents":[],"id":259,"thread":"build-45"},{"duration":0,"stepId":"io.quarkus.mutiny.deployment.MutinyProcessor#buildTimeInit","started":"23:05:10.019","dependents":[416],"id":128,"thread":"build-20"},{"duration":0,"stepId":"io.quarkus.arc.deployment.LifecycleEventsBuildStep#startupEvent","started":"23:05:10.706","dependents":[416,414],"id":412,"thread":"build-34"},{"duration":0,"stepId":"io.quarkus.arc.deployment.AutoAddScopeProcessor#annotationTransformer","started":"23:05:10.233","dependents":[360,358,333],"id":324,"thread":"build-43"},{"duration":0,"stepId":"io.quarkus.jackson.deployment.JacksonProcessor#unremovable","started":"23:05:10.179","dependents":[360,358],"id":270,"thread":"build-42"},{"duration":0,"stepId":"io.quarkus.hibernate.orm.deployment.HibernateOrmProcessor#includeArchivesHostingEntityPackagesInIndex","started":"23:05:10.001","dependents":[242],"id":6,"thread":"build-5"},{"duration":0,"stepId":"io.quarkus.hibernate.orm.deployment.HibernateOrmProcessor#registerHibernateOrmMetadataForCoreDialects","started":"23:05:10.016","dependents":[295],"id":92,"thread":"build-9"},{"duration":0,"stepId":"io.quarkus.deployment.steps.ConfigGenerationBuildStep#mappings","started":"23:05:10.178","dependents":[360,342,363,415,364,340],"id":256,"thread":"build-46"},{"duration":0,"stepId":"io.quarkus.resteasy.deployment.ResteasyBuiltinsProcessor#setUpSecurity","started":"23:05:10.039","dependents":[333,317,328],"id":225,"thread":"build-13"},{"duration":0,"stepId":"io.quarkus.smallrye.openapi.deployment.SmallRyeOpenApiProcessor#logCleanup","started":"23:05:10.016","dependents":[301,239],"id":85,"thread":"build-12"},{"duration":0,"stepId":"io.quarkus.deployment.ConstructorPropertiesProcessor#build","started":"23:05:10.179","dependents":[415],"id":274,"thread":"build-53"},{"duration":0,"stepId":"io.quarkus.devui.deployment.ide.IdeProcessor#createJsonRPCService","started":"23:05:10.166","dependents":[250,286],"id":249,"thread":"build-34"},{"duration":0,"stepId":"io.quarkus.vertx.http.deployment.HttpSecurityProcessor#initFormAuth","started":"23:05:10.010","dependents":[407,345,416,410,350,343,405],"id":39,"thread":"build-3"},{"duration":0,"stepId":"io.quarkus.deployment.dev.testing.TestTracingProcessor#startTesting","started":"23:05:10.027","dependents":[413,411,412,301],"id":181,"thread":"build-38"},{"duration":0,"stepId":"io.quarkus.arc.deployment.StartupBuildSteps#unremovableBeans","started":"23:05:10.018","dependents":[360,358],"id":112,"thread":"build-3"},{"duration":0,"stepId":"io.quarkus.hibernate.orm.panache.deployment.PanacheHibernateResourceProcessor#featureBuildItem","started":"23:05:10.019","dependents":[416],"id":133,"thread":"build-9"},{"duration":0,"stepId":"io.quarkus.resteasy.common.deployment.ResteasyCommonProcessor#resteasyConfig","started":"23:05:10.039","dependents":[328],"id":223,"thread":"build-17"},{"duration":0,"stepId":"io.quarkus.vertx.core.deployment.VertxCoreProcessor#overrideContextInternalInterfaceToAddSafeGuards","started":"23:05:10.019","dependents":[391],"id":122,"thread":"build-3"},{"duration":0,"stepId":"io.quarkus.hibernate.orm.deployment.dev.HibernateOrmDevServicesProcessor#devServicesAutoGenerateByDefault","started":"23:05:10.184","dependents":[305],"id":299,"thread":"build-52"},{"duration":0,"stepId":"io.quarkus.devui.deployment.menu.BuildMetricsProcessor#createBuildMetricsPages","started":"23:05:10.019","dependents":[395],"id":131,"thread":"build-7"},{"duration":0,"stepId":"io.quarkus.devui.deployment.menu.ConfigurationProcessor#createConfigurationPages","started":"23:05:10.187","dependents":[395],"id":306,"thread":"build-36"},{"duration":0,"stepId":"io.quarkus.arc.deployment.ArcProcessor#setupExecutor","started":"23:05:10.015","dependents":[416],"id":68,"thread":"build-4"},{"duration":0,"stepId":"io.quarkus.panache.common.deployment.PanacheHibernateCommonResourceProcessor#replaceFieldAccesses","started":"23:05:10.362","dependents":[391],"id":356,"thread":"build-17"},{"duration":0,"stepId":"io.quarkus.deployment.logging.LoggingResourceProcessor#logConsoleCommand","started":"23:05:10.020","dependents":[314],"id":140,"thread":"build-7"},{"duration":0,"stepId":"io.quarkus.vertx.deployment.VertxProcessor#registerBean","started":"23:05:10.015","dependents":[333,317],"id":76,"thread":"build-6"},{"duration":0,"stepId":"io.quarkus.deployment.ExtensionLoader#booleanSupplierFactory","started":"23:05:10.036","dependents":[204],"id":203,"thread":"build-30"},{"duration":0,"stepId":"io.quarkus.devui.deployment.menu.ContinuousTestingProcessor#createContinuousTestingPages","started":"23:05:10.018","dependents":[395],"id":104,"thread":"build-6"},{"duration":0,"stepId":"io.quarkus.netty.deployment.NettyProcessor#registerEventLoopBeans","started":"23:05:10.019","dependents":[345,416,350,343],"id":134,"thread":"build-20"},{"duration":0,"stepId":"io.quarkus.hibernate.orm.deployment.HibernateLogFilterBuildStep#setupLogFilters","started":"23:05:10.019","dependents":[301,239],"id":124,"thread":"build-8"},{"duration":0,"stepId":"io.quarkus.deployment.steps.BlockingOperationControlBuildStep#blockingOP","started":"23:05:10.024","dependents":[416],"id":167,"thread":"build-21"},{"duration":0,"stepId":"io.quarkus.swaggerui.deployment.SwaggerUiProcessor#feature","started":"23:05:10.001","dependents":[416],"id":11,"thread":"build-9"},{"duration":0,"stepId":"io.quarkus.vertx.http.deployment.devmode.tests.TestsProcessor#printfailures","started":"23:05:10.001","dependents":[403,410],"id":10,"thread":"build-7"},{"duration":0,"stepId":"io.quarkus.deployment.steps.DevServicesConfigBuildStep#deprecated","started":"23:05:10.001","dependents":[305],"id":8,"thread":"build-7"},{"duration":0,"stepId":"io.quarkus.jdbc.postgresql.deployment.PostgreSQLJDBCReflections#build","started":"23:05:10.001","dependents":[415],"id":9,"thread":"build-9"},{"duration":0,"stepId":"io.quarkus.hibernate.orm.deployment.HibernateUserTypeProcessor#build","started":"23:05:10.180","dependents":[415],"id":280,"thread":"build-40"},{"duration":0,"stepId":"io.quarkus.vertx.http.deployment.VertxHttpProcessor#shouldNotRemoveHttpServerOptionsCustomizers","started":"23:05:10.019","dependents":[360,358],"id":127,"thread":"build-3"},{"duration":0,"stepId":"io.quarkus.panache.common.deployment.PanacheHibernateCommonResourceProcessor#findEntityClasses","started":"23:05:10.182","dependents":[356],"id":291,"thread":"build-52"},{"duration":0,"stepId":"io.quarkus.jdbc.postgresql.deployment.JDBCPostgreSQLProcessor#feature","started":"23:05:10.015","dependents":[416],"id":75,"thread":"build-9"},{"duration":0,"stepId":"io.quarkus.vertx.http.deployment.devmode.console.DevConsoleProcessor#builder","started":"23:05:10.166","dependents":[403,410],"id":251,"thread":"build-55"},{"duration":0,"stepId":"io.quarkus.narayana.jta.deployment.NarayanaJtaProcessor#startRecoveryService","started":"23:05:10.314","dependents":[416],"id":348,"thread":"build-17"},{"duration":0,"stepId":"io.quarkus.deployment.steps.ReflectiveHierarchyStep#ignoreJavaClassWarnings","started":"23:05:10.001","dependents":[332],"id":5,"thread":"build-5"},{"duration":0,"stepId":"io.quarkus.deployment.steps.ConfigGenerationBuildStep#suppressNonRuntimeConfigChanged","started":"23:05:10.016","dependents":[159],"id":86,"thread":"build-3"},{"duration":0,"stepId":"io.quarkus.deployment.steps.ConfigGenerationBuildStep#staticInitSources","started":"23:05:10.001","dependents":[369],"id":7,"thread":"build-6"},{"duration":0,"stepId":"io.quarkus.arc.deployment.devconsole.ArcDevConsoleProcessor#monitor","started":"23:05:10.036","dependents":[413,333,317],"id":202,"thread":"build-54"},{"duration":0,"stepId":"io.quarkus.undertow.deployment.UndertowStaticResourcesBuildStep#scanStaticResources","started":"23:05:10.047","dependents":[],"id":243,"thread":"build-46"},{"duration":0,"stepId":"io.quarkus.devui.deployment.menu.ExtensionsProcessor#createExtensionsPages","started":"23:05:10.498","dependents":[395],"id":394,"thread":"build-15"},{"duration":0,"stepId":"io.quarkus.netty.deployment.NettyProcessor#build","started":"23:05:10.003","dependents":[219,415],"id":19,"thread":"build-6"},{"duration":0,"stepId":"io.quarkus.resteasy.common.deployment.ResteasyCommonProcessor#addStaticInitConfigSourceProvider","started":"23:05:10.037","dependents":[369,415],"id":209,"thread":"build-24"},{"duration":0,"stepId":"io.quarkus.arc.deployment.UnremovableAnnotationsProcessor#unremovableBeans","started":"23:05:10.019","dependents":[360,358],"id":126,"thread":"build-2"},{"duration":0,"stepId":"io.quarkus.devui.deployment.DevUIProcessor#createJsonRpcRouter","started":"23:05:10.434","dependents":[416],"id":381,"thread":"build-67"},{"duration":0,"stepId":"io.quarkus.vertx.http.deployment.ManagementInterfaceSecurityProcessor#builtins","started":"23:05:10.025","dependents":[333,317],"id":168,"thread":"build-25"},{"duration":0,"stepId":"io.quarkus.devservices.postgresql.deployment.PostgresqlDevServicesProcessor#psqlCommand","started":"23:05:10.187","dependents":[314],"id":308,"thread":"build-52"},{"duration":0,"stepId":"io.quarkus.resteasy.server.common.deployment.ResteasyServerCommonProcessor#beanDefiningAnnotations","started":"23:05:10.013","dependents":[333,317,200,202],"id":51,"thread":"build-12"},{"duration":0,"stepId":"io.quarkus.devui.deployment.logstream.LogStreamProcessor#additionalBean","started":"23:05:10.018","dependents":[333,317],"id":113,"thread":"build-8"},{"duration":0,"stepId":"io.quarkus.hibernate.orm.deployment.HibernateOrmProcessor#startPersistenceUnits","started":"23:05:10.434","dependents":[413,416,411,412],"id":382,"thread":"build-69"},{"duration":0,"stepId":"io.quarkus.resteasy.common.deployment.ResteasyCommonProcessor#configInjectionStaticInitProvider","started":"23:05:10.000","dependents":[363],"id":4,"thread":"build-3"},{"duration":0,"stepId":"io.quarkus.hibernate.orm.deployment.HibernateOrmProcessor#setupPersistenceProvider","started":"23:05:10.037","dependents":[416,216,382],"id":215,"thread":"build-42"},{"duration":0,"stepId":"io.quarkus.smallrye.openapi.deployment.devui.OpenApiDevUIProcessor#pages","started":"23:05:10.011","dependents":[393,375],"id":49,"thread":"build-4"},{"duration":0,"stepId":"io.quarkus.jackson.deployment.JacksonProcessor#supportMixins","started":"23:05:10.178","dependents":[345,416,350,343,415],"id":263,"thread":"build-55"},{"duration":0,"stepId":"io.quarkus.hibernate.orm.deployment.HibernateOrmProcessor#defineTypeOfImpliedPU","started":"23:05:10.183","dependents":[295,296,302],"id":294,"thread":"build-54"},{"duration":0,"stepId":"io.quarkus.deployment.steps.MainClassBuildStep#applicationReflection","started":"23:05:10.026","dependents":[415],"id":176,"thread":"build-40"},{"duration":0,"stepId":"io.quarkus.arc.deployment.TestsAsBeansProcessor#testAnnotations","started":"23:05:10.015","dependents":[333,317,200,202],"id":59,"thread":"build-11"},{"duration":0,"stepId":"io.quarkus.arc.deployment.ConfigBuildStep#registerConfigClasses","started":"23:05:10.370","dependents":[416],"id":366,"thread":"build-36"},{"duration":0,"stepId":"io.quarkus.vertx.http.deployment.devmode.tests.TestsProcessor#results","started":"23:05:10.021","dependents":[374],"id":148,"thread":"build-8"},{"duration":0,"stepId":"io.quarkus.hibernate.orm.panache.deployment.PanacheHibernateResourceProcessor#recordEntityToPersistenceUnit","started":"23:05:10.362","dependents":[416],"id":357,"thread":"build-54"},{"duration":0,"stepId":"io.quarkus.devui.deployment.logstream.LogStreamProcessor#createJsonRPCService","started":"23:05:10.015","dependents":[250,286],"id":79,"thread":"build-4"},{"duration":0,"stepId":"io.quarkus.hibernate.orm.deployment.HibernateOrmCdiProcessor#convertJpaResourceAnnotationsToQualifier","started":"23:05:10.184","dependents":[333],"id":296,"thread":"build-14"},{"duration":0,"stepId":"io.quarkus.arc.deployment.ReflectiveBeanClassesProcessor#implicitReflectiveBeanClasses","started":"23:05:10.306","dependents":[377],"id":338,"thread":"build-43"},{"duration":0,"stepId":"io.quarkus.arc.deployment.staticmethods.InterceptedStaticMethodsProcessor#callInitializer","started":"23:05:10.434","dependents":[416],"id":379,"thread":"build-43"},{"duration":0,"stepId":"io.quarkus.resteasy.deployment.ResteasyBuiltinsProcessor#addReactiveRoutesExceptionMapper","started":"23:05:10.001","dependents":[416],"id":14,"thread":"build-6"},{"duration":0,"stepId":"io.quarkus.netty.deployment.NettyProcessor#limitArenaSize","started":"23:05:10.023","dependents":[416],"id":162,"thread":"build-21"},{"duration":0,"stepId":"io.quarkus.arc.deployment.ArcProcessor#validateAsyncObserverExceptionHandlers","started":"23:05:10.370","dependents":[377],"id":365,"thread":"build-16"},{"duration":0,"stepId":"io.quarkus.deployment.console.ConsoleProcessor#helpCommand","started":"23:05:10.015","dependents":[314],"id":81,"thread":"build-8"},{"duration":0,"stepId":"io.quarkus.arc.deployment.TestsAsBeansProcessor#testClassBeans","started":"23:05:10.037","dependents":[333,317],"id":205,"thread":"build-33"},{"duration":0,"stepId":"io.quarkus.smallrye.openapi.deployment.SmallRyeOpenApiProcessor#smallryeOpenApiIndex","started":"23:05:10.226","dependents":[326,353,325,327],"id":322,"thread":"build-55"},{"duration":0,"stepId":"io.quarkus.deployment.steps.ConfigGenerationBuildStep#builderMappings","started":"23:05:10.370","dependents":[369,415],"id":367,"thread":"build-17"},{"duration":0,"stepId":"io.quarkus.vertx.http.deployment.devmode.console.DevConsoleProcessor#setupWebJar","started":"23:05:10.017","dependents":[399],"id":99,"thread":"build-2"},{"duration":0,"stepId":"io.quarkus.vertx.http.deployment.VertxHttpProcessor#httpRoot","started":"23:05:10.001","dependents":[408,353,386,14,406,15,82,330],"id":13,"thread":"build-5"},{"duration":0,"stepId":"io.quarkus.datasource.deployment.devservices.DevUIDatasourceProcessor#devConsoleInfo","started":"23:05:10.003","dependents":[374],"id":25,"thread":"build-7"},{"duration":0,"stepId":"io.quarkus.deployment.steps.PreloadClassesBuildStep#registerPreInitClasses","started":"23:05:10.016","dependents":[],"id":84,"thread":"build-9"},{"duration":0,"stepId":"io.quarkus.smallrye.context.deployment.SmallRyeContextPropagationProcessor#createSynthBeansForConfiguredInjectionPoints","started":"23:05:10.306","dependents":[345,416,350,343],"id":339,"thread":"build-29"},{"duration":0,"stepId":"io.quarkus.smallrye.openapi.deployment.SmallRyeOpenApiProcessor#runtimeOnly","started":"23:05:10.004","dependents":[369],"id":30,"thread":"build-3"},{"duration":0,"stepId":"io.quarkus.deployment.ExtensionLoader#config","started":"23:05:10.000","dependents":[49,326,371,295,44,248,217,3,39,209,48,4,216,40,309,317,6,377,27,13,11,259,34,299,245,220,56,16,53,409,229,242,416,18,228,367,33,17,41,360,19,264,353,386,293,189,42,268,185,129,373,391,348,184,323,321,333,28,399,159,38,183,201,284,193,178,164,200,414,246,298,403,329,412,170,25,26,24,336,37,364,162,43,52,222,50,45,269,410,202,297,407,402,368,47,46,411,223,388,389,390,282,383,168,165,404,171,181,304,328,327,57,51,214,198,215,153,54,301,275,408,369,287],"id":1,"thread":"build-2"},{"duration":0,"stepId":"io.quarkus.arc.deployment.ArcProcessor#quarkusMain","started":"23:05:10.015","dependents":[333,317,200,202],"id":78,"thread":"build-20"},{"duration":0,"stepId":"io.quarkus.devui.deployment.DevUIProcessor#createAllRoutes","started":"23:05:10.610","dependents":[404],"id":401,"thread":"build-34"},{"duration":0,"stepId":"io.quarkus.vertx.http.deployment.devmode.BuildMetricsDevConsoleProcessor#collectMetrics","started":"23:05:10.022","dependents":[374],"id":158,"thread":"build-6"},{"duration":0,"stepId":"io.quarkus.smallrye.context.deployment.SmallRyeContextPropagationProcessor#transformInjectionPoint","started":"23:05:10.018","dependents":[333],"id":111,"thread":"build-20"},{"duration":0,"stepId":"io.quarkus.hibernate.orm.deployment.HibernateOrmProcessor#contributePersistenceXmlToJpaModel","started":"23:05:10.033","dependents":[288],"id":190,"thread":"build-17"},{"duration":0,"stepId":"io.quarkus.undertow.deployment.UndertowStaticResourcesBuildStep#handleGeneratedWebResources","started":"23:05:10.037","dependents":[],"id":208,"thread":"build-54"},{"duration":0,"stepId":"io.quarkus.resteasy.common.deployment.ResteasyCommonProcessor#disableDefaultExceptionMapper","started":"23:05:10.025","dependents":[416],"id":171,"thread":"build-28"},{"duration":0,"stepId":"io.quarkus.deployment.steps.RegisterForReflectionBuildStep#build","started":"23:05:10.179","dependents":[332,415],"id":266,"thread":"build-17"},{"duration":0,"stepId":"io.quarkus.vertx.deployment.VertxProcessor#autoAddScope","started":"23:05:10.020","dependents":[324],"id":141,"thread":"build-10"},{"duration":0,"stepId":"io.quarkus.deployment.steps.BannerProcessor#watchBannerChanges","started":"23:05:10.000","dependents":[312],"id":3,"thread":"build-3"},{"duration":0,"stepId":"io.quarkus.vertx.http.deployment.devmode.console.DevConsoleProcessor#setupDevConsoleRoutes_8bb86a3e770caadb970f4facb490e30df7a2a187","started":"23:05:10.610","dependents":[407,416,410,405],"id":400,"thread":"build-15"},{"duration":0,"stepId":"io.quarkus.arc.deployment.ArcProcessor#exposeCustomScopeNames","started":"23:05:10.021","dependents":[151,333,321,324,317,200,329,336,202,275],"id":142,"thread":"build-9"},{"duration":0,"stepId":"io.quarkus.vertx.http.deployment.VertxHttpProcessor#additionalBeans","started":"23:05:10.026","dependents":[333,317],"id":173,"thread":"build-37"},{"duration":0,"stepId":"io.quarkus.devui.deployment.DevUIProcessor#additionalBean","started":"23:05:10.166","dependents":[254,333,317],"id":250,"thread":"build-5"},{"duration":0,"stepId":"io.quarkus.hibernate.orm.deployment.HibernateOrmProcessor#produceLoggingCategories","started":"23:05:10.027","dependents":[179],"id":178,"thread":"build-17"},{"duration":0,"stepId":"io.quarkus.deployment.steps.ReflectiveHierarchyStep#build","started":"23:05:10.250","dependents":[415],"id":332,"thread":"build-14"},{"duration":0,"stepId":"io.quarkus.deployment.steps.ShutdownListenerBuildStep#setupShutdown","started":"23:05:10.642","dependents":[416],"id":409,"thread":"build-55"},{"duration":0,"stepId":"io.quarkus.smallrye.openapi.deployment.SmallRyeOpenApiProcessor#contributeClassesToIndex","started":"23:05:10.021","dependents":[254],"id":155,"thread":"build-9"},{"duration":0,"stepId":"io.quarkus.vertx.deployment.EventBusCodecProcessor#registerCodecs","started":"23:05:10.226","dependents":[344,415],"id":319,"thread":"build-17"},{"duration":0,"stepId":"io.quarkus.arc.deployment.BuildTimeEnabledProcessor#ifBuildProfile","started":"23:05:10.179","dependents":[329,279,278],"id":267,"thread":"build-35"},{"duration":0,"stepId":"io.quarkus.deployment.dev.testing.TestTracingProcessor#handle","started":"23:05:10.021","dependents":[301,239],"id":145,"thread":"build-3"},{"duration":0,"stepId":"io.quarkus.arc.deployment.WrongAnnotationUsageProcessor#detect","started":"23:05:10.306","dependents":[377],"id":336,"thread":"build-43"},{"duration":0,"stepId":"io.quarkus.smallrye.openapi.deployment.SmallRyeOpenApiProcessor#registerJaxRsSupportedAnnotation","started":"23:05:10.018","dependents":[329],"id":103,"thread":"build-3"},{"duration":0,"stepId":"io.quarkus.deployment.dev.ConfigureDisableInstrumentationBuildStep#configure","started":"23:05:10.026","dependents":[413,411,412],"id":174,"thread":"build-31"},{"duration":0,"stepId":"io.quarkus.arc.deployment.ConfigBuildStep#registerCustomConfigBeanTypes","started":"23:05:10.306","dependents":[345,350,343,415],"id":337,"thread":"build-14"},{"duration":0,"stepId":"io.quarkus.vertx.http.deployment.devmode.console.DevConsoleProcessor#setupDevConsoleWebjar","started":"23:05:10.033","dependents":[399],"id":194,"thread":"build-52"},{"duration":0,"stepId":"io.quarkus.arc.deployment.BuildTimeEnabledProcessor#conditionTransformer","started":"23:05:10.180","dependents":[333],"id":278,"thread":"build-16"},{"duration":0,"stepId":"io.quarkus.deployment.steps.CurateOutcomeBuildStep#curateOutcome","started":"23:05:10.029","dependents":[217,304,206,186,375,185,273,391,204,311,229,242,393,374,187,403,410,396,188,286,399,202],"id":184,"thread":"build-14"},{"duration":0,"stepId":"io.quarkus.vertx.core.deployment.VertxCoreProcessor#doNotRemoveVertxOptionsCustomizers","started":"23:05:10.016","dependents":[360,358],"id":93,"thread":"build-4"},{"duration":0,"stepId":"io.quarkus.devui.deployment.build.BuildMetricsDevUIProcessor#createJsonRPCService","started":"23:05:10.034","dependents":[250,286],"id":195,"thread":"build-53"},{"duration":0,"stepId":"io.quarkus.arc.deployment.ConfigBuildStep#registerConfigMappingsBean","started":"23:05:10.306","dependents":[351],"id":340,"thread":"build-14"},{"duration":0,"stepId":"io.quarkus.deployment.steps.NativeImageConfigBuildStep#build","started":"23:05:10.038","dependents":[416],"id":219,"thread":"build-53"},{"duration":0,"stepId":"io.quarkus.deployment.steps.ConfigGenerationBuildStep#extensionMappings","started":"23:05:10.178","dependents":[360,342,363,415,364,340],"id":269,"thread":"build-26"},{"duration":0,"stepId":"io.quarkus.deployment.logging.LoggingResourceProcessor#registerMetrics","started":"23:05:10.004","dependents":[416,301],"id":27,"thread":"build-10"},{"duration":0,"stepId":"io.quarkus.vertx.http.deployment.devmode.tests.TestsProcessor#toggleInstrumentation","started":"23:05:10.043","dependents":[403,410],"id":238,"thread":"build-51"},{"duration":0,"stepId":"io.quarkus.hibernate.orm.deployment.HibernateOrmProcessor#configurationDescriptorBuilding","started":"23:05:10.183","dependents":[392,298,299,416,300,296,302,297,303,312],"id":295,"thread":"build-45"},{"duration":0,"stepId":"io.quarkus.hibernate.orm.deployment.metrics.HibernateOrmMetricsProcessor#metrics","started":"23:05:10.037","dependents":[416],"id":216,"thread":"build-53"},{"duration":0,"stepId":"io.quarkus.resteasy.deployment.ResteasyServletProcessor#addServletsToExceptionMapper","started":"23:05:10.442","dependents":[416],"id":385,"thread":"build-28"},{"duration":0,"stepId":"io.quarkus.arc.deployment.StartupBuildSteps#registerStartupObservers","started":"23:05:10.322","dependents":[358],"id":352,"thread":"build-17"},{"duration":0,"stepId":"io.quarkus.arc.deployment.ArcProcessor#buildCompatibleExtensions","started":"23:05:10.003","dependents":[333,317],"id":23,"thread":"build-7"},{"duration":0,"stepId":"io.quarkus.vertx.http.deployment.devmode.tests.TestsProcessor#toggleTestOutput","started":"23:05:10.015","dependents":[403,410],"id":64,"thread":"build-9"},{"duration":0,"stepId":"io.quarkus.narayana.jta.deployment.NarayanaJtaProcessor#unremovableBean","started":"23:05:10.015","dependents":[360,358],"id":83,"thread":"build-4"},{"duration":0,"stepId":"io.quarkus.devui.deployment.build.BuildMetricsDevUIProcessor#create","started":"23:05:10.018","dependents":[416],"id":116,"thread":"build-9"},{"duration":0,"stepId":"io.quarkus.arc.deployment.ArcProcessor#launchMode","started":"23:05:10.033","dependents":[333,317],"id":191,"thread":"build-42"},{"duration":0,"stepId":"io.quarkus.arc.deployment.ObserverValidationProcessor#validateApplicationObserver","started":"23:05:10.370","dependents":[377],"id":361,"thread":"build-14"},{"duration":0,"stepId":"io.quarkus.deployment.steps.CapabilityAggregationStep#aggregateCapabilities","started":"23:05:10.037","dependents":[243,207,208,295,353,386,293,376,217,266,304,268,328,302,270,303,209,218,222,333,331,214,210,215,227,297,211,384,223,225,414,213,282,224,294,228,212,325],"id":206,"thread":"build-30"},{"duration":0,"stepId":"io.quarkus.arc.deployment.LoggingBeanSupportProcessor#discoveredComponents","started":"23:05:10.015","dependents":[333,317,200,202],"id":69,"thread":"build-11"},{"duration":0,"stepId":"io.quarkus.arc.deployment.ConfigBuildStep#validateConfigPropertiesInjectionPoints","started":"23:05:10.370","dependents":[366],"id":364,"thread":"build-40"},{"duration":0,"stepId":"io.quarkus.deployment.dev.io.NioThreadPoolDevModeProcessor#setupTCCL","started":"23:05:10.021","dependents":[416],"id":154,"thread":"build-2"},{"duration":0,"stepId":"io.quarkus.hibernate.orm.deployment.dev.HibernateOrmDevUIProcessor#create","started":"23:05:10.016","dependents":[393,375],"id":94,"thread":"build-9"},{"duration":0,"stepId":"io.quarkus.agroal.deployment.AgroalProcessor#agroal","started":"23:05:10.017","dependents":[416],"id":96,"thread":"build-8"},{"duration":0,"stepId":"io.quarkus.devservices.postgresql.deployment.PostgresqlDevServicesProcessor#setupPostgres","started":"23:05:10.026","dependents":[304],"id":175,"thread":"build-39"},{"duration":0,"stepId":"io.quarkus.hibernate.orm.deployment.HibernateOrmCdiProcessor#registerAnnotations","started":"23:05:10.036","dependents":[333,317,200,202],"id":199,"thread":"build-22"},{"duration":0,"stepId":"io.quarkus.arc.deployment.HotDeploymentConfigBuildStep#configFile","started":"23:05:10.019","dependents":[312],"id":137,"thread":"build-11"},{"duration":0,"stepId":"io.quarkus.arc.deployment.devui.ArcDevUIProcessor#createJsonRPCService","started":"23:05:10.019","dependents":[250,286],"id":117,"thread":"build-6"},{"duration":0,"stepId":"io.quarkus.deployment.pkg.steps.PackageTypeVerificationBuildStep#verify","started":"23:05:10.033","dependents":[413,411,412],"id":193,"thread":"build-42"},{"duration":0,"stepId":"io.quarkus.jdbc.postgresql.deployment.JDBCPostgreSQLProcessor#registerServiceBinding","started":"23:05:10.037","dependents":[217,304],"id":213,"thread":"build-26"},{"duration":0,"stepId":"io.quarkus.deployment.console.ConsoleProcessor#quitCommand","started":"23:05:10.018","dependents":[314],"id":108,"thread":"build-8"},{"duration":0,"stepId":"io.quarkus.arc.deployment.ConfigBuildStep#validateConfigValues","started":"23:05:10.434","dependents":[416,415],"id":380,"thread":"build-71"},{"duration":0,"stepId":"io.quarkus.deployment.logging.LoggingResourceProcessor#setupLogFilters","started":"23:05:10.021","dependents":[301,239],"id":144,"thread":"build-20"},{"duration":0,"stepId":"io.quarkus.narayana.jta.deployment.NarayanaJtaProcessor#registerScope","started":"23:05:10.019","dependents":[142],"id":136,"thread":"build-8"},{"duration":0,"stepId":"io.quarkus.devui.deployment.build.BuildMetricsDevUIProcessor#additionalBeans","started":"23:05:10.039","dependents":[333,317],"id":221,"thread":"build-35"},{"duration":0,"stepId":"io.quarkus.vertx.http.deployment.VertxHttpProcessor#notFoundRoutes","started":"23:05:10.634","dependents":[406],"id":405,"thread":"build-34"},{"duration":0,"stepId":"io.quarkus.deployment.SslProcessor#setupNativeSsl","started":"23:05:10.024","dependents":[219,293,166,227],"id":165,"thread":"build-27"},{"duration":0,"stepId":"io.quarkus.jdbc.postgresql.deployment.JDBCPostgreSQLProcessor#registerDriver","started":"23:05:10.024","dependents":[217],"id":166,"thread":"build-18"},{"duration":0,"stepId":"io.quarkus.devui.deployment.menu.DevServicesProcessor#createDevServicesPages","started":"23:05:10.217","dependents":[395],"id":315,"thread":"build-43"},{"duration":0,"stepId":"io.quarkus.vertx.http.deployment.VertxHttpProcessor#frameworkRoot","started":"23:05:10.010","dependents":[407,400,371,49,402,408,180,63,390,397,403,410,309,82,396,404,395],"id":43,"thread":"build-9"},{"duration":0,"stepId":"io.quarkus.hibernate.orm.deployment.HibernateOrmProcessor#checkTransactionsSupport","started":"23:05:10.037","dependents":[377],"id":212,"thread":"build-41"},{"duration":0,"stepId":"io.quarkus.jackson.deployment.JacksonProcessor#autoRegisterModules","started":"23:05:10.178","dependents":[283],"id":260,"thread":"build-33"},{"duration":0,"stepId":"io.quarkus.hibernate.orm.panache.deployment.PanacheHibernateResourceProcessor#collectEntityClasses","started":"23:05:10.179","dependents":[355],"id":277,"thread":"build-47"},{"duration":0,"stepId":"io.quarkus.vertx.http.deployment.devmode.console.ConfigEditorProcessor#handleRequests","started":"23:05:10.187","dependents":[403,410],"id":307,"thread":"build-45"},{"duration":0,"stepId":"io.quarkus.hibernate.orm.panache.deployment.PanacheHibernateResourceProcessor#ensureBeanLookupAvailable","started":"23:05:10.015","dependents":[360,358],"id":67,"thread":"build-20"},{"duration":0,"stepId":"io.quarkus.arc.deployment.devui.ArcDevUIProcessor#pages","started":"23:05:10.386","dependents":[393,375],"id":373,"thread":"build-29"},{"duration":0,"stepId":"io.quarkus.resteasy.deployment.ResteasyServletProcessor#build","started":"23:05:10.442","dependents":[385,416,415],"id":384,"thread":"build-25"},{"duration":0,"stepId":"io.quarkus.deployment.logging.LoggingResourceProcessor#setUpDefaultLogCleanupFilters","started":"23:05:10.043","dependents":[368],"id":239,"thread":"build-49"},{"duration":0,"stepId":"io.quarkus.jdbc.postgresql.deployment.JDBCPostgreSQLProcessor#devDbHandler","started":"23:05:10.020","dependents":[304],"id":138,"thread":"build-8"},{"duration":0,"stepId":"io.quarkus.arc.deployment.CommandLineArgumentsProcessor#commandLineArgs","started":"23:05:10.018","dependents":[345,333,317,350,343],"id":109,"thread":"build-20"},{"duration":0,"stepId":"io.quarkus.netty.deployment.NettyProcessor#cleanupMacDNSInLog","started":"23:05:10.015","dependents":[301,239],"id":58,"thread":"build-9"},{"duration":0,"stepId":"io.quarkus.hibernate.orm.deployment.dev.HibernateOrmDevUIProcessor#createJsonRPCService","started":"23:05:10.018","dependents":[250,286],"id":118,"thread":"build-7"},{"duration":0,"stepId":"io.quarkus.smallrye.openapi.deployment.SmallRyeOpenApiProcessor#additionalBean","started":"23:05:10.017","dependents":[333,317],"id":95,"thread":"build-20"},{"duration":0,"stepId":"io.quarkus.resteasy.common.deployment.ResteasyCommonProcessor#setupGzipProviders","started":"23:05:10.003","dependents":[328],"id":24,"thread":"build-6"},{"duration":0,"stepId":"io.quarkus.hibernate.orm.deployment.HibernateOrmProcessor#addPersistenceUnitAnnotationToIndex","started":"23:05:10.015","dependents":[254],"id":70,"thread":"build-20"},{"duration":0,"stepId":"io.quarkus.hibernate.orm.deployment.HibernateOrmCdiProcessor#validatePersistenceUnitExtensions","started":"23:05:10.370","dependents":[377],"id":362,"thread":"build-29"},{"duration":0,"stepId":"io.quarkus.arc.deployment.ConfigBuildStep#registerConfigPropertiesBean","started":"23:05:10.306","dependents":[351],"id":342,"thread":"build-29"},{"duration":0,"stepId":"io.quarkus.deployment.DockerStatusProcessor#IsDockerWorking","started":"23:05:10.004","dependents":[313,304],"id":31,"thread":"build-6"},{"duration":0,"stepId":"io.quarkus.resteasy.common.deployment.ResteasyCommonProcessor#registerJsonContextResolvers","started":"23:05:10.179","dependents":[360,358,333,317,328],"id":268,"thread":"build-22"},{"duration":0,"stepId":"io.quarkus.vertx.core.deployment.VertxCoreProcessor#filterNettyHostsFileParsingWarn","started":"23:05:10.019","dependents":[301,239],"id":123,"thread":"build-11"},{"duration":0,"stepId":"io.quarkus.agroal.deployment.AgroalMetricsProcessor#registerMetrics","started":"23:05:10.038","dependents":[416],"id":220,"thread":"build-42"},{"duration":0,"stepId":"io.quarkus.arc.deployment.staticmethods.InterceptedStaticMethodsProcessor#processInterceptedStaticMethods","started":"23:05:10.314","dependents":[355,415,391,356,354],"id":349,"thread":"build-45"},{"duration":0,"stepId":"io.quarkus.hibernate.orm.deployment.HibernateOrmAlwaysEnabledProcessor#featureBuildItem","started":"23:05:10.015","dependents":[416],"id":74,"thread":"build-15"},{"duration":0,"stepId":"io.quarkus.vertx.http.deployment.VertxHttpProcessor#openSocket","started":"23:05:10.706","dependents":[416,415],"id":414,"thread":"build-15"},{"duration":0,"stepId":"io.quarkus.netty.deployment.NettyProcessor#eagerlyInitClass","started":"23:05:10.016","dependents":[416],"id":89,"thread":"build-6"},{"duration":0,"stepId":"io.quarkus.arc.deployment.AutoInjectFieldProcessor#annotationTransformer","started":"23:05:10.233","dependents":[333],"id":323,"thread":"build-17"},{"duration":0,"stepId":"io.quarkus.vertx.http.deployment.devmode.tests.TestsProcessor#toggleLiveReloadEnabled","started":"23:05:10.017","dependents":[403,410],"id":101,"thread":"build-3"},{"duration":0,"stepId":"io.quarkus.deployment.steps.ApplicationInfoBuildStep#create","started":"23:05:10.003","dependents":[416],"id":17,"thread":"build-5"},{"duration":0,"stepId":"io.quarkus.deployment.logging.LoggingResourceProcessor#setUpDefaultLevels","started":"23:05:10.027","dependents":[368,301],"id":179,"thread":"build-38"},{"duration":0,"stepId":"io.quarkus.arc.deployment.ArcProcessor#signalBeanContainerReady","started":"23:05:10.434","dependents":[408,383,379,416,380,388,412,382,387,381],"id":378,"thread":"build-49"},{"duration":0,"stepId":"io.quarkus.agroal.deployment.AgroalProcessor#adaptOpenTelemetryJdbcInstrumentationForNative","started":"23:05:10.039","dependents":[391],"id":224,"thread":"build-16"},{"duration":0,"stepId":"io.quarkus.hibernate.orm.deployment.HibernateOrmProcessor#pregenProxies","started":"23:05:10.482","dependents":[416],"id":392,"thread":"build-15"},{"duration":0,"stepId":"io.quarkus.deployment.pkg.steps.PackageTypeVerificationBuildStep#builtins","started":"23:05:10.033","dependents":[193],"id":192,"thread":"build-47"},{"duration":0,"stepId":"io.quarkus.hibernate.orm.deployment.HibernateOrmProcessor#warnOfSchemaProblems","started":"23:05:10.706","dependents":[416],"id":411,"thread":"build-15"},{"duration":0,"stepId":"io.quarkus.arc.deployment.devui.ArcDevUIProcessor#registerMonitoringComponents","started":"23:05:10.036","dependents":[333,317],"id":200,"thread":"build-29"},{"duration":0,"stepId":"io.quarkus.resteasy.deployment.RestPathAnnotationProcessor#registerBeanClasses","started":"23:05:10.037","dependents":[333,317],"id":207,"thread":"build-33"},{"duration":0,"stepId":"io.quarkus.vertx.http.deployment.VertxHttpProcessor#logging","started":"23:05:10.022","dependents":[179],"id":157,"thread":"build-8"},{"duration":0,"stepId":"io.quarkus.hibernate.orm.deployment.HibernateOrmProcessor#hotDeploymentWatchedFiles","started":"23:05:10.003","dependents":[312],"id":26,"thread":"build-3"},{"duration":0,"stepId":"io.quarkus.vertx.http.deployment.devmode.tests.TestsProcessor#handleTestStatus","started":"23:05:10.021","dependents":[403,410],"id":156,"thread":"build-3"},{"duration":0,"stepId":"io.quarkus.deployment.steps.ReflectionDiagnosticProcessor#writeReflectionData","started":"23:05:10.706","dependents":[],"id":415,"thread":"build-34"},{"duration":0,"stepId":"io.quarkus.caffeine.deployment.CaffeineProcessor#cacheLoaders","started":"23:05:10.179","dependents":[415],"id":272,"thread":"build-30"}],"started":"2023-08-25T23:05:09.999","items":[{"count":873,"class":"io.quarkus.deployment.builditem.ConfigDescriptionBuildItem"},{"count":107,"class":"io.quarkus.deployment.builditem.GeneratedClassBuildItem"},{"count":106,"class":"io.quarkus.deployment.builditem.nativeimage.ReflectiveClassBuildItem"},{"count":62,"class":"io.quarkus.deployment.builditem.MainBytecodeRecorderBuildItem"},{"count":50,"class":"io.quarkus.deployment.builditem.BytecodeTransformerBuildItem"},{"count":49,"class":"io.quarkus.arc.deployment.SyntheticBeanBuildItem"},{"count":41,"class":"io.quarkus.vertx.http.deployment.RouteBuildItem"},{"count":40,"class":"io.quarkus.deployment.builditem.StaticBytecodeRecorderBuildItem"},{"count":37,"class":"io.quarkus.vertx.http.deployment.devmode.console.DevTemplatePathBuildItem"},{"count":35,"class":"io.quarkus.arc.deployment.AdditionalBeanBuildItem"},{"count":35,"class":"io.quarkus.deployment.builditem.nativeimage.RuntimeInitializedClassBuildItem"},{"count":27,"class":"io.quarkus.deployment.builditem.RunTimeConfigurationDefaultBuildItem"},{"count":26,"class":"io.quarkus.deployment.builditem.HotDeploymentWatchedFileBuildItem"},{"count":20,"class":"io.quarkus.devconsole.spi.DevConsoleRouteBuildItem"},{"count":17,"class":"io.quarkus.deployment.logging.LogCleanupFilterBuildItem"},{"count":15,"class":"io.quarkus.arc.deployment.UnremovableBeanBuildItem"},{"count":13,"class":"io.quarkus.deployment.builditem.nativeimage.ReflectiveHierarchyBuildItem"},{"count":13,"class":"io.quarkus.resteasy.common.spi.ResteasyJaxrsProviderBuildItem"},{"count":13,"class":"io.quarkus.deployment.builditem.CapabilityBuildItem"},{"count":12,"class":"io.quarkus.deployment.builditem.FeatureBuildItem"},{"count":10,"class":"io.quarkus.deployment.builditem.AdditionalIndexedClassesBuildItem"},{"count":9,"class":"io.quarkus.resteasy.server.common.spi.AllowedJaxRsAnnotationPrefixBuildItem"},{"count":8,"class":"io.quarkus.vertx.http.deployment.devmode.NotFoundPageDisplayableEndpointBuildItem"},{"count":8,"class":"io.quarkus.vertx.http.deployment.webjar.WebJarBuildItem"},{"count":8,"class":"io.quarkus.devui.spi.JsonRPCProvidersBuildItem"},{"count":8,"class":"io.quarkus.hibernate.orm.deployment.spi.DatabaseKindDialectBuildItem"},{"count":7,"class":"io.quarkus.arc.deployment.AnnotationsTransformerBuildItem"},{"count":7,"class":"io.quarkus.deployment.builditem.ConsoleCommandBuildItem"},{"count":7,"class":"io.quarkus.deployment.pkg.builditem.PackageTypeBuildItem"},{"count":6,"class":"io.quarkus.deployment.builditem.SystemPropertyBuildItem"},{"count":6,"class":"io.quarkus.devui.deployment.DevUIWebJarBuildItem"},{"count":6,"class":"io.quarkus.devui.deployment.DevUIRoutesBuildItem"},{"count":6,"class":"io.quarkus.deployment.builditem.nativeimage.NativeImageSystemPropertyBuildItem"},{"count":5,"class":"io.quarkus.devui.deployment.InternalPageBuildItem"},{"count":5,"class":"io.quarkus.deployment.builditem.RunTimeConfigBuilderBuildItem"},{"count":5,"class":"io.quarkus.arc.deployment.BeanDefiningAnnotationBuildItem"},{"count":5,"class":"io.quarkus.deployment.builditem.SuppressNonRuntimeConfigChangedWarningBuildItem"},{"count":5,"class":"io.quarkus.devconsole.spi.DevConsoleTemplateInfoBuildItem"},{"count":5,"class":"io.quarkus.deployment.builditem.nativeimage.NativeImageResourceBuildItem"},{"count":5,"class":"io.quarkus.devui.deployment.BuildTimeConstBuildItem"},{"count":5,"class":"io.quarkus.devui.spi.page.CardPageBuildItem"},{"count":4,"class":"io.quarkus.devconsole.spi.DevConsoleRuntimeTemplateInfoBuildItem"},{"count":4,"class":"io.quarkus.deployment.builditem.AdditionalApplicationArchiveMarkerBuildItem"},{"count":4,"class":"io.quarkus.deployment.builditem.ServiceStartBuildItem"},{"count":3,"class":"io.quarkus.vertx.http.deployment.FilterBuildItem"},{"count":3,"class":"io.quarkus.deployment.builditem.StaticInitConfigBuilderBuildItem"},{"count":3,"class":"io.quarkus.deployment.builditem.nativeimage.ReflectiveMethodBuildItem"},{"count":3,"class":"io.quarkus.jackson.spi.ClassPathJacksonModuleBuildItem"},{"count":3,"class":"io.quarkus.vertx.http.deployment.HttpSecurityPolicyBuildItem"},{"count":3,"class":"io.quarkus.hibernate.orm.panache.common.deployment.PanacheNamedQueryEntityClassBuildStep"},{"count":3,"class":"io.quarkus.deployment.builditem.GeneratedResourceBuildItem"},{"count":2,"class":"io.quarkus.deployment.builditem.ShutdownListenerBuildItem"},{"count":2,"class":"io.quarkus.deployment.builditem.ObjectSubstitutionBuildItem"},{"count":2,"class":"io.quarkus.arc.deployment.AutoAddScopeBuildItem"},{"count":2,"class":"io.quarkus.devui.spi.buildtime.QuteTemplateBuildItem"},{"count":2,"class":"io.quarkus.deployment.builditem.nativeimage.NativeImageConfigBuildItem"},{"count":2,"class":"io.quarkus.smallrye.openapi.deployment.spi.AddToOpenAPIDefinitionBuildItem"},{"count":2,"class":"io.quarkus.deployment.builditem.BytecodeRecorderObjectLoaderBuildItem"},{"count":2,"class":"io.quarkus.devui.spi.buildtime.StaticContentBuildItem"},{"count":2,"class":"io.quarkus.devui.deployment.InternalImportMapBuildItem"},{"count":2,"class":"io.quarkus.deployment.builditem.LogCategoryBuildItem"},{"count":1,"class":"io.quarkus.devui.deployment.MvnpmBuildItem"},{"count":1,"class":"io.quarkus.deployment.builditem.AnnotationProxyBuildItem"},{"count":1,"class":"io.quarkus.deployment.builditem.TransformedClassesBuildItem"},{"count":1,"class":"io.quarkus.deployment.builditem.BytecodeRecorderConstantDefinitionBuildItem"},{"count":1,"class":"io.quarkus.netty.deployment.EventLoopGroupBuildItem"},{"count":1,"class":"io.quarkus.hibernate.orm.deployment.JpaModelIndexBuildItem"},{"count":1,"class":"io.quarkus.arc.deployment.devui.ArcBeanInfoBuildItem"},{"count":1,"class":"io.quarkus.vertx.http.deployment.spi.StaticResourcesBuildItem"},{"count":1,"class":"io.quarkus.datasource.deployment.spi.DevServicesDatasourceConfigurationHandlerBuildItem"},{"count":1,"class":"io.quarkus.deployment.console.ConsoleInstalledBuildItem"},{"count":1,"class":"io.quarkus.arc.deployment.BeanDiscoveryFinishedBuildItem"},{"count":1,"class":"io.quarkus.resteasy.common.spi.ResteasyConfigBuildItem"},{"count":1,"class":"io.quarkus.deployment.builditem.RunTimeConfigurationProxyBuildItem"},{"count":1,"class":"io.quarkus.arc.deployment.SynthesisFinishedBuildItem"},{"count":1,"class":"io.quarkus.vertx.http.deployment.DefaultRouteBuildItem"},{"count":1,"class":"io.quarkus.vertx.core.deployment.EventLoopCountBuildItem"},{"count":1,"class":"io.quarkus.resteasy.common.deployment.JaxrsProvidersToRegisterBuildItem"},{"count":1,"class":"io.quarkus.vertx.core.deployment.CoreVertxBuildItem"},{"count":1,"class":"io.quarkus.arc.deployment.BuildCompatibleExtensionsBuildItem"},{"count":1,"class":"io.quarkus.devui.deployment.ThemeVarsBuildItem"},{"count":1,"class":"io.quarkus.datasource.deployment.spi.DefaultDataSourceDbKindBuildItem"},{"count":1,"class":"io.quarkus.hibernate.orm.deployment.JpaModelPersistenceUnitMappingBuildItem"},{"count":1,"class":"io.quarkus.deployment.builditem.DockerStatusBuildItem"},{"count":1,"class":"io.quarkus.deployment.builditem.nativeimage.ReflectiveHierarchyIgnoreWarningBuildItem"},{"count":1,"class":"io.quarkus.arc.deployment.InterceptorResolverBuildItem"},{"count":1,"class":"io.quarkus.vertx.http.deployment.InitialRouterBuildItem"},{"count":1,"class":"io.quarkus.panache.common.deployment.HibernateMetamodelForFieldAccessBuildItem"},{"count":1,"class":"io.quarkus.smallrye.openapi.deployment.spi.OpenApiDocumentBuildItem"},{"count":1,"class":"io.quarkus.deployment.dev.ExceptionNotificationBuildItem"},{"count":1,"class":"io.quarkus.deployment.dev.devservices.DevServiceDescriptionBuildItem"},{"count":1,"class":"io.quarkus.swaggerui.deployment.SwaggerUiBuildItem"},{"count":1,"class":"io.quarkus.panache.common.deployment.HibernateEnhancersRegisteredBuildItem"},{"count":1,"class":"io.quarkus.arc.deployment.ValidationPhaseBuildItem"},{"count":1,"class":"io.quarkus.netty.deployment.EventLoopSupplierBuildItem"},{"count":1,"class":"io.quarkus.deployment.builditem.DevServicesResultBuildItem"},{"count":1,"class":"io.quarkus.arc.deployment.BeanArchiveIndexBuildItem"},{"count":1,"class":"io.quarkus.deployment.builditem.ConsoleFormatterBannerBuildItem"},{"count":1,"class":"io.quarkus.arc.deployment.SuppressConditionGeneratorBuildItem"},{"count":1,"class":"io.quarkus.deployment.builditem.ApplicationArchivesBuildItem"},{"count":1,"class":"io.quarkus.deployment.BooleanSupplierFactoryBuildItem"},{"count":1,"class":"io.quarkus.deployment.builditem.ContextHandlerBuildItem"},{"count":1,"class":"io.quarkus.hibernate.orm.deployment.ImpliedBlockingPersistenceUnitTypeBuildItem"},{"count":1,"class":"io.quarkus.arc.deployment.TransformedAnnotationsBuildItem"},{"count":1,"class":"io.quarkus.deployment.builditem.GeneratedFileSystemResourceHandledBuildItem"},{"count":1,"class":"io.quarkus.datasource.deployment.spi.DevServicesDatasourceProviderBuildItem"},{"count":1,"class":"io.quarkus.deployment.builditem.DevServicesLauncherConfigResultBuildItem"},{"count":1,"class":"io.quarkus.hibernate.orm.deployment.PersistenceProviderSetUpBuildItem"},{"count":1,"class":"io.quarkus.deployment.pkg.builditem.OutputTargetBuildItem"},{"count":1,"class":"io.quarkus.resteasy.deployment.ResteasyJaxrsConfigBuildItem"},{"count":1,"class":"io.quarkus.panache.common.deployment.PanacheEntityClassesBuildItem"},{"count":1,"class":"io.quarkus.resteasy.server.common.spi.ResteasyJaxrsConfigBuildItem"},{"count":1,"class":"io.quarkus.arc.deployment.PreBeanContainerBuildItem"},{"count":1,"class":"io.quarkus.deployment.builditem.ThreadFactoryBuildItem"},{"count":1,"class":"io.quarkus.vertx.http.deployment.devmode.console.DevConsoleProcessor$HistoryHandlerBuildItem"},{"count":1,"class":"io.quarkus.arc.deployment.InjectionPointTransformerBuildItem"},{"count":1,"class":"io.quarkus.deployment.builditem.ApplicationIndexBuildItem"},{"count":1,"class":"io.quarkus.panache.common.deployment.HibernateModelClassCandidatesForFieldAccessBuildItem"},{"count":1,"class":"io.quarkus.vertx.http.deployment.webjar.WebJarResultsBuildItem"},{"count":1,"class":"io.quarkus.hibernate.orm.deployment.JpaModelPersistenceUnitContributionBuildItem"},{"count":1,"class":"io.quarkus.agroal.spi.JdbcDriverBuildItem"},{"count":1,"class":"io.quarkus.smallrye.openapi.deployment.OpenApiFilteredIndexViewBuildItem"},{"count":1,"class":"io.quarkus.vertx.http.deployment.NonApplicationRootPathBuildItem"},{"count":1,"class":"io.quarkus.vertx.http.deployment.VertxWebRouterBuildItem"},{"count":1,"class":"io.quarkus.deployment.builditem.CombinedIndexBuildItem"},{"count":1,"class":"io.quarkus.devui.deployment.JsonRPCMethodsBuildItem"},{"count":1,"class":"io.quarkus.deployment.Capabilities"},{"count":1,"class":"io.quarkus.arc.deployment.GeneratedBeanBuildItem"},{"count":1,"class":"io.quarkus.devui.deployment.ExtensionsBuildItem"},{"count":1,"class":"io.quarkus.deployment.logging.LoggingSetupBuildItem"},{"count":1,"class":"io.quarkus.deployment.builditem.ExecutorBuildItem"},{"count":1,"class":"io.quarkus.deployment.builditem.WebSocketLogHandlerBuildItem"},{"count":1,"class":"io.quarkus.deployment.dev.testing.TestListenerBuildItem"},{"count":1,"class":"io.quarkus.resteasy.common.deployment.ResteasyInjectionReadyBuildItem"},{"count":1,"class":"io.quarkus.deployment.builditem.ExtensionSslNativeSupportBuildItem"},{"count":1,"class":"io.quarkus.smallrye.context.deployment.spi.ThreadContextProviderBuildItem"},{"count":1,"class":"io.quarkus.arc.deployment.BeanRegistrationPhaseBuildItem"},{"count":1,"class":"io.quarkus.arc.deployment.ObserverRegistrationPhaseBuildItem"},{"count":1,"class":"io.quarkus.deployment.builditem.ApplicationClassNameBuildItem"},{"count":1,"class":"io.quarkus.vertx.http.deployment.SecurityInformationBuildItem"},{"count":1,"class":"io.quarkus.deployment.builditem.StreamingLogHandlerBuildItem"},{"count":1,"class":"io.quarkus.deployment.dev.DisableInstrumentationForIndexPredicateBuildItem"},{"count":1,"class":"io.quarkus.resteasy.server.common.deployment.ResteasyServerConfigBuildItem"},{"count":1,"class":"io.quarkus.hibernate.orm.deployment.JpaModelBuildItem"},{"count":1,"class":"io.quarkus.vertx.deployment.VertxBuildItem"},{"count":1,"class":"io.quarkus.arc.deployment.BeanContainerBuildItem"},{"count":1,"class":"io.quarkus.hibernate.orm.deployment.spi.AdditionalJpaModelBuildItem"},{"count":1,"class":"io.quarkus.arc.deployment.CurrentContextFactoryBuildItem"},{"count":1,"class":"io.quarkus.deployment.ide.EffectiveIdeBuildItem"},{"count":1,"class":"io.quarkus.resteasy.deployment.ResteasyStandaloneBuildStep$ResteasyStandaloneBuildItem"},{"count":1,"class":"io.quarkus.deployment.pkg.builditem.CurateOutcomeBuildItem"},{"count":1,"class":"io.quarkus.vertx.http.deployment.HttpRootPathBuildItem"},{"count":1,"class":"io.quarkus.deployment.builditem.ConfigurationBuildItem"},{"count":1,"class":"io.quarkus.deployment.steps.CapabilityAggregationStep$CapabilitiesConfiguredInDescriptorsBuildItem"},{"count":1,"class":"io.quarkus.deployment.builditem.ApplicationStartBuildItem"},{"count":1,"class":"io.quarkus.deployment.builditem.ApplicationClassPredicateBuildItem"},{"count":1,"class":"io.quarkus.vertx.http.deployment.BodyHandlerBuildItem"},{"count":1,"class":"io.quarkus.agroal.deployment.AggregatedDataSourceBuildTimeConfigBuildItem"},{"count":1,"class":"io.quarkus.arc.deployment.BuildExclusionsBuildItem"},{"count":1,"class":"io.quarkus.deployment.builditem.LogCategoryMinLevelDefaultsBuildItem"},{"count":1,"class":"io.quarkus.arc.deployment.ContextRegistrationPhaseBuildItem"},{"count":1,"class":"io.quarkus.arc.deployment.ConfigInjectionStaticInitBuildItem"},{"count":1,"class":"io.quarkus.arc.deployment.CustomScopeAnnotationsBuildItem"},{"count":1,"class":"io.quarkus.deployment.builditem.IOThreadDetectorBuildItem"},{"count":1,"class":"io.quarkus.deployment.builditem.SslNativeConfigBuildItem"},{"count":1,"class":"io.quarkus.hibernate.orm.deployment.PersistenceUnitDescriptorBuildItem"},{"count":1,"class":"io.quarkus.arc.deployment.CustomScopeBuildItem"},{"count":1,"class":"io.quarkus.resteasy.server.common.deployment.ResteasyDeploymentBuildItem"},{"count":1,"class":"io.quarkus.arc.deployment.ContextRegistrationPhaseBuildItem$ContextConfiguratorBuildItem"},{"count":1,"class":"io.quarkus.arc.deployment.AutoInjectAnnotationBuildItem"},{"count":1,"class":"io.quarkus.arc.deployment.CompletedApplicationClassPredicateBuildItem"},{"count":1,"class":"io.quarkus.agroal.spi.JdbcDataSourceBuildItem"},{"count":1,"class":"io.quarkus.deployment.builditem.StaticInitConfigSourceFactoryBuildItem"},{"count":1,"class":"io.quarkus.deployment.builditem.ApplicationInfoBuildItem"},{"count":1,"class":"io.quarkus.deployment.builditem.ConfigClassBuildItem"},{"count":1,"class":"io.quarkus.hibernate.orm.panache.deployment.EntityToPersistenceUnitBuildItem"},{"count":1,"class":"io.quarkus.deployment.ide.IdeRunningProcessBuildItem"},{"count":1,"class":"io.quarkus.arc.deployment.BeanContainerListenerBuildItem"},{"count":1,"class":"io.quarkus.deployment.ide.IdeFileBuildItem"},{"count":1,"class":"io.quarkus.deployment.builditem.MainClassBuildItem"}],"itemsCount":1899,"buildTarget":"quarkus-topicos1-2023-2-1.0.0-SNAPSHOT"}